[
  {
    "essay_id": "GWGR2400107330.1",
    "status": "ok",
    "prediction": {
      "content": {
        "score": 4.0,
        "rationale": "에세이는 잊힐 권리에 대한 주요 논점을 잘 제시하고 있으며, 찬반 양론을 균형 있게 다루고 있다. 개인 정보 보호와 사생활 보장의 필요성을 언급하며 긍정적인 측면을 설명하고, 알 권리 및 언론의 자유와의 충돌 가능성을 지적하며 부정적인 측면을 설명하는 등 주장이 명확하다. 그러나 근거 제시가 다소 피상적이며, 각 논점의 구체적인 사례나 통계 자료를 추가하면 더욱 설득력 있는 에세이가 될 수 있었다."
      },
      "organization": {
        "score": 4.0,
        "rationale": "에세이는 서론, 본론, 결론의 구조가 명확하게 드러나 있다. 서론에서는 잊힐 권리에 대한 배경과 논점을 간략하게 소개하고, 본론에서는 찬성 및 반대 입장을 각각 제시하며 논리적으로 전개된다. 결론에서는 두 입장 사이의 균형점을 찾으려는 시도를 보이며 마무리한다. 문단 간 연결도 자연스럽고, 논리 흐름이 비교적 일관적이다. 다만, 각 문단의 내용이 조금 더 구체화되면 더욱 효과적인 글이 될 수 있었다."
      },
      "expression": {
        "score": 4.0,
        "rationale": "에세이의 문장은 대체로 자연스럽고 이해하기 쉽다. 어휘 사용도 적절하며, 문법적인 오류나 맞춤법 문제도 발견되지 않았다. 주술 호응도 비교적 정확하게 사용되었다. 그러나 문장 표현이 다소 단조롭고, 일부 구체적인 예시를 추가하면 더욱 풍부하고 생동감 있는 글이 될 수 있었다."
      }
    },
    "judge": {
      "content": {
        "round_0": {
          "strict": {
            "domain_match": 5,
            "score_rationale_consistency": 4,
            "specificity": 3,
            "groundedness": 5,
            "overall_judge": 4.2,
            "rationale_for_score": "1. domain_match: rationale 은 target_domain(content) 의 평가 기준인 주장의 명확성, 찬반 양론의 균형적 다루기, 근거 제시 등을 정확히 반영하고 있습니다. 2. score_rationale_consistency: predicted_score(4.0) 는 '주요 논점 잘 제시', '균형 있는 논의'라는 강점과 '근거 피상적'이라는 약점을 모두 포함하여 점수를 정당화합니다. 높은 점수임에도 불구하고 구체적인 사례나 통계 자료 부재라는 명확한 약점이 있으므로 5점보다는 4점으로 처리했습니다. 3. specificity: '개인 정보 보호', '알 권리', '기술적 문제점' 등 에세이 내의 구체적 논지를 인용하고 있으나, '피상적'이라는 평가에 대한 구체적인 문장 예시 (예: '왜 피상적인가? 어떤 부분이 부족했는가') 가 명시적으로 누락되어 있습니다. 4. groundedness: rationale 의 모든 내용은 essay_text 에서 확인 가능한 내용으로, 허구나 과장이 없습니다."
          },
          "lenient": {
            "domain_match": 5,
            "score_rationale_consistency": 5,
            "specificity": 4,
            "groundedness": 5,
            "overall_judge": 4.8,
            "rationale_for_score": "1) domain_match: rationale 가 'content' 영역의 평가 기준 (주장 명확성, 찬반 균형, 근거 제시 등) 을 정확히 적용하여 에세이의 논리적 구조를 분석함. 2) score_rationale_consistency: predicted_score(4.0) 와 rationale 의 설명이 완벽하게 일치함. 에세이가 핵심 논지를 잘 다루고 있으나 근거가 피상적이라는 지적은 '매우 좋음'에 준하는 4 점의 합리적 정당화임. 3) specificity: '개인 정보 보호', '알 권리 충돌', '기술적 문제점' 등 에세이 내 구체적 논거를 직접 언급하며 평가함. 4) groundedness: rationale 의 모든 지적 (찬반 양론, 근거 부족) 이 essay_text 의 실제 내용과 정확히 일치하여 hallucination 이 없음."
          }
        },
        "round_1": {
          "strict": {
            "domain_match": 5,
            "score_rationale_consistency": 5,
            "specificity": 4,
            "groundedness": 5,
            "overall_judge": 4.8,
            "adjustment_notes": "관대한 심사위원의 평가는 rationale 텍스트에 명시된 근거 (주장 명확성, 찬반 균형, 근거 피상성 지적 등) 를 모두 인정하고 있습니다. 따라서 domain_match, score_rationale_consistency, groundedness 항목은 기존 5 점 유지합니다. specificity 항목은 '개인 정보 보호', '알 권리 충돌' 등 구체적 논거 언급이 있어 관대한 심사위원의 4 점 평가가 타당하므로 유지합니다. 전체적으로 관대한 심사위원이 제시한 근거 (에세이의 강점과 약점을 명확히 구분하고, '근거가 피상적'이라는 구체적인 지적을 통해 4 점의 정당성을 확보함) 에 따라 점수를 조정할 필요가 없으므로 overall_judge 를 4.0 으로 유지합니다."
          },
          "lenient": {
            "domain_match": 5,
            "score_rationale_consistency": 4,
            "specificity": 2,
            "groundedness": 5,
            "overall_judge": 3.0,
            "adjustment_notes": "1. domain_match: 엄격한 심사위원의 평가 (5점) 를 유지합니다. rationale 은 content 영역의 핵심 기준인 주장 명확성, 찬반 균형, 근거 제시를 정확히 반영하고 있습니다.\n2. score_rationale_consistency: 엄격한 심사위원의 평가 (4점) 를 유지합니다. predicted_score(4.0) 에 '주요 논점 잘 제시'라는 강점과 '근거 피상적'이라는 약점이 모두 포함되어 점수가 정당화됩니다.\n3. specificity: 기존 3점을 2점으로 하향 조정합니다. 엄격한 심사위원은 '피상적'이라는 평가에 대한 구체적인 문장 예시나 부족함의 구체적 지시가 누락되었다고 지적했습니다. 이는 '구체적 예시 없음' 감점 기준에 해당하므로, generic 표현만 사용된 것으로 간주하여 점수를 낮추었습니다.\n4. groundedness: 엄격한 심사위원의 평가 (5점) 를 유지합니다. rationale 의 모든 내용은 essay_text 에서 확인 가능한 사실에 기반하고 있으며 허구가 없습니다."
          }
        },
        "round_2": {
          "strict": {
            "domain_match": 5,
            "score_rationale_consistency": 4,
            "specificity": 2,
            "groundedness": 5,
            "overall_judge": 3.0,
            "adjustment_notes": "관대한 심사위원의 평가 결과를 바탕으로 각 항목을 재검토한 결과, 기존 점수를 유지합니다.\n1. domain_match: rationale 이 content 영역의 핵심 요소 (주장 명확성, 찬반 균형) 를 정확히 반영하고 있어 5점 유지.\n2. score_rationale_consistency: '근거 피상적'이라는 약점을 명시적으로 언급하여 4점 예측 점수를 정당화하므로 4점 유지.\n3. specificity: 관대한 심사위원이 '피상적'이라는 표현에 대한 구체적 문장 예시 누락을 지적했으나, 이는 rationale 텍스트 내부의 설명 부족을 의미합니다. 따라서 generic 표현만 사용된 것으로 간주하여 2점 유지.\n4. groundedness: rationale 의 모든 내용은 essay_text 에서 확인 가능한 사실 (개인정보 보호, 알 권리 충돌 등) 에 기반하므로 5점 유지."
          },
          "lenient": {
            "domain_match": 5,
            "score_rationale_consistency": 5,
            "specificity": 4,
            "groundedness": 5,
            "overall_judge": 4.8,
            "adjustment_notes": "엄격한 심사위원의 평가는 관대한 심사위원이 제시한 rationale 의 근거 (주장 명확성, 찬반 균형, 근거 피상성 지적) 를 모두 수용하여 점수를 유지했습니다. domain_match, score_rationale_consistency, groundedness 항목은 rationale 이 에세이의 논지를 정확히 반영하고 있으며, 구체적인 사례나 통계 자료 부재라는 지적이 essay_text 의 내용과 일치하므로 기존 5 점 및 4 점 평가가 타당합니다. 따라서 모든 항목의 점수와 전체 점수는 조정 없이 유지합니다."
          }
        },
        "final": {
          "domain_match": 5.0,
          "score_rationale_consistency": 4.5,
          "specificity": 3.0,
          "groundedness": 5.0,
          "overall_judge": 3.9
        }
      },
      "organization": {
        "round_0": {
          "strict": {
            "domain_match": 5,
            "score_rationale_consistency": 4,
            "specificity": 4,
            "groundedness": 5,
            "overall_judge": 4.5,
            "rationale_for_score": "1. domain_match: rationale 은 서론 - 본론 - 결론의 구조적 분석과 논리 흐름 평가 등 organization 도메인의 핵심 기준을 명확히 준수함. 2. score_rationale_consistency: predicted_score(4.0)는 '구조가 명확하지만 구체성이 부족하다'는 설명과 일치하나, '매우 효과적이다'라는 표현보다는 '조금 더 구체화되면'이라는 경미한 개선점 지적이 있어 완벽한 5점은 아님. 3. specificity: '서론', '본론', '결론', '문단 간 연결' 등 구체적인 구조적 요소를 언급했으나, '각 문단의 내용이 조금 더 구체화되면'이라는 표현은 다소 추상적임 (구체적인 어떤 내용을 추가해야 하는지 명시되지 않음). 4. groundedness: rationale 의 모든 주장 (서론 배경 소개, 본론 찬반 제시, 결론 균형점 모색) 은 essay_text 의 실제 내용과 정확히 일치함."
          },
          "lenient": {
            "domain_match": 5,
            "score_rationale_consistency": 5,
            "specificity": 5,
            "groundedness": 5,
            "overall_judge": 5.0,
            "rationale_for_score": "1. domain_match: rationale 가 organization 영역의 서론/본론/결론 구조, 문단 연결, 논리 흐름 등 평가 기준을 정확히 적용함. 2. score_rationale_consistency: predicted_score(4.0) 는 '구조가 명확하고 논리적'이라는 강점과 '내용 구체화 부족'이라는 약점을 모두 반영하여 점수 정당화가 완벽함. 3. specificity: 서론의 배경 소개, 본론의 찬반 입장 제시, 결론의 균형점 모색 등 구체적인 문단 기능과 내용을 지적함. 4. groundedness: rationale 의 모든 내용은 essay_text 의 실제 구조와 내용 (서론-본론-결론 배치, 찬반 논지, 종합 제안) 과 정확히 일치하며 hallucination 이 없음."
          }
        },
        "round_1": {
          "strict": {
            "domain_match": 5,
            "score_rationale_consistency": 5,
            "specificity": 5,
            "groundedness": 5,
            "overall_judge": 5.0,
            "adjustment_notes": "관대한 심사위원의 평가가 타당하나, 점수 조정 원칙에 따라 '4점'을 유지합니다. rationale 은 essay_text 의 서론/본론/결론 구조와 구체적인 논지 (개인정보 보호 vs 알 권리 충돌 등) 를 정확히 반영하여 groundedness 와 specificity 기준을 충족합니다. 또한 높은 점수 (4.0) 에 대한 근거가 명확하고, 약점 (구체화 부족) 도 명시되어 score_rationale_consistency 가 완벽합니다. domain_match 역시 organization 영역의 구조적 평가 기준을 준수하므로 감점 사유가 없습니다."
          },
          "lenient": {
            "domain_match": 5,
            "score_rationale_consistency": 4,
            "specificity": 3,
            "groundedness": 5,
            "overall_judge": 4.2,
            "adjustment_notes": "1. domain_match: 엄격한 심사위원의 평가대로 organization 도메인의 구조적 분석 기준을 명확히 준수하므로 기존 5점 유지. 2. score_rationale_consistency: '구조는 명확하나 구체성이 부족하다'는 설명이 점수 4.0 과 일치하므로 기존 4점 유지. 3. specificity: 엄격한 심사위원이 지적한 대로 '각 문단의 내용을 구체화하면'이라는 표현은 구체적인 개선 방안 (예: 어떤 근거를 더 보강할 것 등) 이 명시되지 않아 추상적임. 따라서 감점하여 3점으로 조정. 4. groundedness: rationale 의 모든 주장이 essay_text 의 실제 내용과 일치하므로 기존 5점 유지."
          }
        },
        "round_2": {
          "strict": {
            "domain_match": 5,
            "score_rationale_consistency": 4,
            "specificity": 3,
            "groundedness": 5,
            "overall_judge": 4.2,
            "adjustment_notes": "관대한 심사위원의 평가 내용을 바탕으로 각 항목을 재검토한 결과, 기존 점수를 유지합니다. 1) domain_match: rationale 이 서론-본론-결론의 구조적 분석에 초점을 맞추어 organization 도메인의 기준을 명확히 준수하므로 5점 유지. 2) score_rationale_consistency: '구조는 명확하나 구체성이 부족하다'는 설명이 점수 4.0 과 일치하며, 높은 점수에 비해 약점이 명시되어 있으므로 모순이 없어 4점 유지. 3) specificity: '각 문단의 내용을 조금 더 구체화되면'이라는 표현은 구체적인 개선 방안이나 예시 없이 추상적인 피드백에 그치므로 엄격한 기준에 따라 3점으로 조정 (관대한 심사위원의 감점 결정과 일치). 4) groundedness: rationale 의 모든 주장이 essay_text 의 실제 내용과 일치하며 허구가 없으므로 5점 유지."
          },
          "lenient": {
            "domain_match": 5,
            "score_rationale_consistency": 5,
            "specificity": 4,
            "groundedness": 5,
            "overall_judge": 4.8,
            "adjustment_notes": "관대한 심사위원의 평가가 타당합니다. domain_match 는 organization 영역의 구조적 기준을 명확히 준수하며, score_rationale_consistency 는 높은 점수 (4.0) 에 대한 근거 (구조 명확성, 논리 일관성) 와 약점 지적이 일치합니다. groundedness 는 essay_text 의 서론/본론/결론 내용과 정확히 연결됩니다. specificity 기준에서 '구체적 예시 없음'으로 5점을 유지하기보다 4점으로 조정하는 것이 더 엄격하고 타당합니다. rationale 은 '각 문단의 내용이 조금 더 구체화되면...'이라는 일반적인 제언만 제시하고, essay_text 에서 구체적인 어떤 부분이 부족했는지 (예: 개인정보 보호 근거의 구체성 등) 를 명시적으로 지적하지 않았기 때문입니다. 따라서 specificity 기준을 4점으로 하되, 나머지 항목과 전체 점수는 기존 평가가 타당하므로 유지합니다."
          }
        },
        "final": {
          "domain_match": 5.0,
          "score_rationale_consistency": 4.5,
          "specificity": 3.5,
          "groundedness": 5.0,
          "overall_judge": 4.5
        }
      },
      "expression": {
        "round_0": {
          "strict": {
            "domain_match": 5,
            "score_rationale_consistency": 4,
            "specificity": 3,
            "groundedness": 3,
            "overall_judge": 3.8,
            "rationale_for_score": "1. domain_match: rationale이 'expression' 영역의 평가 기준 (문장 자연스러움, 어휘 적절함, 문법/맞춤법, 주술 호응) 을 명확히 준수하고 있어 5점 만점. 2. score_rationale_consistency: predicted_score가 4.0으로 높은 편인데, rationale이 '다소 단조롭고 예시 부족'이라는 약점을 지적하여 점수를 낮추려는 시도는 있으나, 구체적인 문장 인용 없이 일반적 평론에 그쳐 설득력이 다소 부족함 (4점). 3. specificity: '문장이 자연스럽다', '어휘 사용 적절하다' 등 평가 대상의 구체적 표현을 직접 인용하지 않고 추상적 형용사만 사용하여 구체성이 떨어짐 (3점). 4. groundedness: essay_text에 존재하는 구체적인 문장이나 단어를 지칭하여 근거를 제시하지 않고, 전체적인 느낌을 바탕으로 판단하여 객관성 확보가 어려움 (3점)."
          },
          "lenient": {
            "domain_match": 5,
            "score_rationale_consistency": 5,
            "specificity": 4,
            "groundedness": 5,
            "overall_judge": 4.8,
            "rationale_for_score": "1) domain_match: rationale 가 'expression' 영역의 평가 기준 (문장 자연스러움, 어휘 적절성, 문법/맞춤법, 주술 호응) 을 명확히 준수하며 평가하고 있습니다. 2) score_rationale_consistency: predicted_score(4.0) 는 '대체로 자연스럽다'는 긍정적 평가와 '단조롭다', '구체적 예시 부재'라는 경미한 약점을 동시에 언급하여 점수를 정당화하므로 모순이 없습니다. 3) specificity: '문장 표현이 다소 단조롭고', '일부 구체적인 예시를 추가하면...'과 같이 문체의 한계와 개선 방향을 구체적으로 지적하고 있습니다. 다만, '어휘 사용도 적절하며'라는 표현은 다소 일반적이라 4점으로 처리했습니다. 4) groundedness: rationale 의 모든 내용은 essay_text 의 마지막 단락 ('따라서 국민 개개인이 갖는 권리들이 조화를 이루어 발전할 수 있도록 하는 방안이 필요하다.')에서 드러나는 추상적인 결론과 논의의 흐름을 바탕으로 하고 있으며, hallucination 이 없습니다."
          }
        },
        "round_1": {
          "strict": {
            "domain_match": 5,
            "score_rationale_consistency": 4,
            "specificity": 3,
            "groundedness": 2,
            "overall_judge": 3.0,
            "adjustment_notes": "1) domain_match: 관대한 심사위원의 평가가 'expression' 영역 기준을 명확히 준수하므로 유지합니다.\n2) score_rationale_consistency: 점수 (4.0) 와 근거 ('대체로 자연스럽다', '단조롭다') 가 일치하지만, 관대한 심사위원이 '어휘 사용도 적절하며'라는 일반적 표현을 경미한 약점으로 4점으로 낮췄음에도 불구하고, 본 평가 기준에 따르면 '경미한 약점 1 개 이하'인 경우 4 점 유지가 가능하므로 관대심사위원의 판단을 존중하여 4 점으로 유지합니다.\n3) specificity: 관대한 심사위원이 '문장 표현이 다소 단조롭고', '구체적 예시 부재'를 지적했으나, 이는 essay_text 의 내용 (논리적 전개와 결론 부분) 을 반영한 추상적 평가지, 구체적인 문장 번호나 특정 표현을 인용하지 않았습니다. 따라서 '구체적 예시 없음'으로 감점하여 3 점으로 조정합니다.\n4) groundedness: 관대한 심사위원이 rationale 의 근거를 essay_text 의 마지막 단락의 '추상적인 결론'과 연결했다고 평가했으나, 이는 hallucination 에 해당합니다. '문장이 단조롭다'는 표현은 essay_text 의 어떤 문장도 구체적으로 지칭하지 않으며, '구체적 예시 추가'라는 제안은 텍스트에 존재하는 사실적 근거가 아닙니다. 따라서 essay_text 와의 직접 연결이 확인되지 않아 2 점으로 감점합니다."
          },
          "lenient": {
            "domain_match": 5,
            "score_rationale_consistency": 4,
            "specificity": 3,
            "groundedness": 3,
            "overall_judge": 3.8,
            "adjustment_notes": "엄격한 심사위원의 평가에 동의합니다. domain_match는 expression 영역 기준을 명확히 따르고 있어 5점 유지합니다. score_rationale_consistency는 높은 점수 (4.0) 에 비해 '단조로움'이라는 약점을 지적하는 근거가 구체적 문장 인용이 없어 설득력이 부족하므로 4점 유지합니다. specificity와 groundedness는 rationale이 추상적 형용사만 사용하고 essay_text의 구체적 표현을 인용하지 않아 각각 3점으로 평가됩니다. 따라서 기존 점수인 3.8점을 유지합니다."
          }
        },
        "round_2": {
          "strict": {
            "domain_match": 5,
            "score_rationale_consistency": 4,
            "specificity": 3,
            "groundedness": 3,
            "overall_judge": 3.8,
            "adjustment_notes": "관대한 심사위원의 평가에 동의합니다. domain_match는 expression 영역 기준을 명확히 따르고 있어 5점 유지합니다. score_rationale_consistency는 높은 점수 (4.0) 에 비해 '단조로움'이라는 약점을 지적하는 근거가 구체적 문장 인용이 없어 설득력이 부족하므로 4점 유지합니다. specificity와 groundedness는 rationale이 추상적 형용사만 사용하고 essay_text의 구체적 표현을 인용하지 않아 각각 3점으로 평가됩니다. 따라서 기존 점수인 3.8점을 유지합니다."
          },
          "lenient": {
            "domain_match": 5,
            "score_rationale_consistency": 4,
            "specificity": 3,
            "groundedness": 2,
            "overall_judge": 3.0,
            "adjustment_notes": "1) domain_match: 관대한 심사위원이 'expression' 영역 기준을 명확히 준수했으므로 유지합니다.\n2) score_rationale_consistency: 점수 (4.0) 와 근거 ('대체로 자연스럽다', '단조롭다') 가 일치하며, 경미한 약점 1 개 이하에 해당하므로 관대한 심사위원의 판단을 존중하여 4 점으로 유지합니다.\n3) specificity: 관대한 심사위원이 '문장 표현이 다소 단조롭고', '구체적 예시 부재'를 지적했으나, 이는 essay_text 의 특정 문장을 인용하지 않은 추상적 평가지라 감점하여 3 점으로 조정합니다.\n4) groundedness: 관대한 심사위원이 rationale 의 근거를 essay_text 와 직접 연결하지 못했다고 평가했으나, '문장이 단조롭다'는 표현은 텍스트의 실제 문장과 구체적으로 매핑되지 않았으므로 hallucination 으로 간주하고 감점하여 2 점으로 조정합니다."
          }
        },
        "final": {
          "domain_match": 5.0,
          "score_rationale_consistency": 4.0,
          "specificity": 3.0,
          "groundedness": 2.5,
          "overall_judge": 3.4
        }
      }
    }
  }
]