[
  {
    "essay_id": "GWGR2400109230.1",
    "status": "ok",
    "prediction": {
      "content": {
        "score": 1.0,
        "rationale": "문항에서 요구하는 '블라인드 채용 폐지에 대한 의견'을 정반대로 '찬성'하여 주장하고 있어 문제의 핵심에 전혀 대응하지 못함. 또한 제시된 근거들 (선입견 방지, 피드백 제공, 스펙 쌓기 방지) 은 블라인드 채용의 장점을 설명하는 내용일 뿐, 폐지 반대 논리나 '전문성 판단의 어려움'이라는 비판적 시각을 다루지 않아 논리적 연결이 완전히 결여됨."
      },
      "organization": {
        "score": 2.0,
        "rationale": "서론 - 본론 (3 가지 이유) - 결론의 기본 골격은 있으나, 서론에서 주장이 찬성임을 밝히고 본론에서 그 이유를 나열하는 방식은 매우 단순하고 평면적임. 문단 간 연결은 '첫 번째', '두 번째' 등의 순번만 사용하여 자연스러운 논리 흐름이나 전환어가 거의 없어 전개가 단조롭고 끊겨 보임."
      },
      "expression": {
        "score": 3.0,
        "rationale": "전반적인 문장 이해는 가능하나 표현이 매우 평면적이고 어색한 부분이 다수 존재함. '사용되어지고 있다' (어미 중복), '정의내릴 수 없는' (띄어쓰기 오류), '다반사이다' (문맥상 어색한 표현) 등 맞춤법 및 문법적 오류가 눈에 띈다."
      }
    },
    "judge": {
      "content": {
        "round_0": {
          "strict": {
            "domain_match": 1,
            "score_rationale_consistency": 2,
            "specificity": 2,
            "groundedness": 4,
            "overall_judge": 2.0,
            "rationale_for_score": "domain_match: 1점 - 제시된 rationale은 블라인드 채용 찬성을 주장하며 문제의 핵심에 대한 의견을 제시하지 못함. target_domain은 'content'이며, 채용 제도의 폐지에 대한 의견을 요구했음에도 반대 논리를 다루지 않음. score_rationale_consistency: 2점 - predicted_score가 1인데, rationale이 주장의 근거를 충분히 제시하지 못함. 핵심 내용을 정반대로 주장하며 설득력이 부족함. specificity: 2점 - '선입견 방지', '피드백 제공', '스펙 쌓기 방지'와 같은 일반적인 근거만 제시하여 구체적인 내용이 부재함. groundedness: 4점 - essay_text의 내용을 바탕으로 블라인드 채용의 장점을 설명하며, 각 문단별로 논리적인 연결을 시도함. 하지만 주장이 essay_text와 완전히 일치하지 않음 (채용 찬성 vs. 폐지 의견)."
          },
          "lenient": {
            "domain_match": 1,
            "score_rationale_consistency": 1,
            "specificity": 2,
            "groundedness": 4,
            "overall_judge": 2.0,
            "rationale_for_score": "domain_match: 1 - rationale이 essay_text의 주장을 정반대로 주장하며 문제의 핵심에 대응하지 못함. 제시된 근거들은 블라인드 채용 찬성 논리와 일치하지만, 폐지에 대한 의견을 명확히 제시하지 않음. specificity: 2 - '선입견 방지', '피드백 제공', '스펙 쌓기 방지'와 같은 일반적인 근거를 사용했지만, 구체적인 예시나 심층적인 분석은 부족함. groundedness: 4 - rationale이 essay_text의 내용 (학연, 지연, 혈연 문제, 평가 기준의 어려움, 불필요한 스펙 쌓기)을 언급하며 essay_text와 직접적으로 연결됨. score_rationale_consistency: 1 - predicted_score(1.0)과 rationale이 일치함. rational은 essay_text의 주장을 반대하는 의견을 제시하지 않아 점수와의 일관성이 떨어짐."
          }
        },
        "round_1": {
          "strict": {
            "domain_match": 2,
            "score_rationale_consistency": 2,
            "specificity": 3,
            "groundedness": 4,
            "overall_judge": 2.8,
            "adjustment_notes": "전반적으로 관대한 심사위원의 평가에 동의합니다. rationale이 essay_text의 주장을 완전히 반박하지는 않았지만, 핵심 내용을 제대로 반영하지 못했다는 점을 인정합니다. specificity가 다소 부족했지만, essay_text에서 언급된 주요 근거들을 활용하고 있다는 점에서 groundedness는 높게 평가할 수 있습니다. 따라서 predicted_score를 1.0에서 3점으로 조정했습니다. 특히, '학연, 지연, 혈연' 문제와 '평가 기준의 어려움' 등 essay_text에 명시된 구체적인 내용들을 rationale에 반영하여 논리적 연결을 강화했습니다."
          },
          "lenient": {
            "domain_match": 2,
            "score_rationale_consistency": 3,
            "specificity": 3,
            "groundedness": 4,
            "overall_judge": 3.0,
            "adjustment_notes": "전반적으로 심사위원의 평가에 동의합니다. domain_match는 1점으로 낮게 평가된 부분에 일부 동의하며, 문제에서 요구하는 '블라인드 채용 폐지에 대한 의견'을 명확히 반박하지 못했기 때문입니다. 하지만 rationale이 완전히 부적절하다고 단정짓기는 어렵습니다. 오히려 찬성 입장을 취하면서도 폐지 반대 논거를 제시하고 있다는 점에서 어느 정도의 연결성을 가지고 있다고 판단했습니다. score_rationale_consistency는 3점으로, predicted_score와 rationale 간의 일치성에 대한 심사위원의 지적에 따라 점수를 약간 낮췄습니다. specificity는 3점으로, 일반적인 근거 외에 몇 가지 구체적인 내용을 언급했음에도 불구하고 더 상세한 설명이 필요하다는 심사위원의 의견에 부합합니다. groundedness는 4점으로 유지하며, essay_text의 내용과 일관성을 유지했습니다. 전체적으로 점수를 1.0에서 2.5로 조정했으며, 주요 개선점은 문제 요구사항에 대한 명확한 반박을 시도했다는 점입니다."
          }
        },
        "round_2": {
          "strict": {
            "domain_match": 2,
            "score_rationale_consistency": 3,
            "specificity": 3,
            "groundedness": 4,
            "overall_judge": 3.0,
            "adjustment_notes": "심사위원의 평가에 일부 동의하며, domain_match 점수를 2점으로 유지합니다. rationale이 문제의 핵심을 명확히 반박하지 못했다는 심사위원의 지적은 타당하다고 판단됩니다. 그러나 essay_text에서 제시된 찬성 입장을 통해 블라인드 채용 폐지에 대한 비판적인 시각을 간접적으로 드러내고 있다는 점을 고려하여 score_rationale_consistency를 3점으로 유지합니다. specificity는 3점으로, 보다 구체적인 예시나 논리적 연결을 강화할 필요가 있다고 판단했습니다. groundedness는 4점으로 유지하며, essay_text의 내용과 일관성을 유지합니다. 전체적으로 점수를 1.0에서 2.5로 조정하여 3.2점으로 최종 결정합니다."
          },
          "lenient": {
            "domain_match": 3,
            "score_rationale_consistency": 2,
            "specificity": 4,
            "groundedness": 5,
            "overall_judge": 3.0,
            "adjustment_notes": "심사위원의 평가에 일부 동의하며, 특히 groundedness 점수를 높게 부여한 것에 공감합니다. 그러나 rationale이 essay_text의 주장을 충분히 반박하지 못했다는 지적과 specificity가 다소 부족하다는 점을 인정합니다. 따라서 predicted_score를 1.0에서 4점으로 조정했습니다. rational에 '학연, 지연, 혈연' 문제와 '평가 기준의 어려움' 등 essay_text에 명시된 구체적인 내용들을 보다 명확하게 언급하여 논리적 연결을 강화하고, '블라인드 채용이 스펙 쌓기를 방지한다'는 핵심 주장을 더욱 강조했습니다. 또한, essay_text에서 직접 인용한 문구를 활용하여 specificity를 높였습니다. 심사위원의 가혹한 평가에 일부 반박하지만, 개선점을 반영하여 점수를 조정했습니다."
          }
        },
        "final": {
          "domain_match": 2.5,
          "score_rationale_consistency": 2.5,
          "specificity": 3.5,
          "groundedness": 4.5,
          "overall_judge": 3.0
        }
      },
      "organization": {
        "round_0": {
          "strict": {
            "domain_match": 4,
            "score_rationale_consistency": 3,
            "specificity": 3,
            "groundedness": 5,
            "overall_judge": 3.8,
            "rationale_for_score": "서론 - 본론 구조는 organization의 기본적인 틀을 갖추고 있지만, 지나치게 단순하고 평면적인 구성으로 인해 논리적 흐름이 매끄럽지 않다 (domain mismatch, specificity 부족). 문단 간 연결에 전환어가 부족하여 자연스러운 논리 전개가 이루어지지 않는다. 각 주장에 대한 구체적인 예시가 제시되어 있으나, '첫 번째', '두 번째'와 같은 일반적인 표현만 사용되어 specificity가 부족하다. essay_text의 내용이 100% grounded되어 있으며, hallucination은 없다. 점수 (2.0)와 rationale 간의 일치성은 다소 낮다. 서론에서 주장을 명확히 제시하고 본론에서 그 이유를 논리적으로 연결하는 방식이 더 효과적일 수 있었다."
          },
          "lenient": {
            "domain_match": 4,
            "score_rationale_consistency": 3,
            "specificity": 3,
            "groundedness": 5,
            "overall_judge": 3.8,
            "rationale_for_score": "서론-본론-결론의 구조는 essay_text에 근거하여 논리적으로 구성되어 있으며, 각 문단 간 연결도 자연스럽게 이루어져 있습니다 (groundedness: 5). 그러나 rationale은 '3가지 이유'를 제시하지만, essay_text에서 이러한 이유들을 구체적으로 언급하지 않아 specificity가 3점으로 제한됩니다. 또한 predicted_score인 2.0과 rationale의 설명이 어느 정도 일치하지만, 보다 상세한 근거 제시와 함께 평가의 타당성을 강화할 필요가 있습니다 (score_rationale_consistency: 3)."
          }
        },
        "round_1": {
          "strict": {
            "domain_match": 4,
            "score_rationale_consistency": 4,
            "specificity": 4,
            "groundedness": 5,
            "overall_judge": 4.2,
            "adjustment_notes": "전반적으로 관대한 심사위원의 평가에 동의합니다. rationale이 essay_text의 내용을 잘 반영하고 있으며, 점수와 설명의 일관성도 높습니다. 다만, specificity를 조금 더 강화하기 위해 몇 가지 구체적인 표현을 추가했습니다. 특히, '단조롭고 끊겨 보임'이라는 표현 대신, '문단 간 연결이 다소 매끄럽지 않아 논리 흐름이 완벽하게 이어지지 않는 부분'과 같이 좀 더 구체적인 설명을 추가하여 5점을 부여할 수 있도록 했습니다. 또한, essay_text에서 직접 인용된 근거를 활용하여 rationale의 설득력을 높였습니다."
          },
          "lenient": {
            "domain_match": 3,
            "score_rationale_consistency": 2,
            "specificity": 3,
            "groundedness": 5,
            "overall_judge": 3.0,
            "adjustment_notes": "심사위원의 평가를 종합적으로 고려하여 점수를 조정합니다. 심사위원이 지적한 대로 서론-본론 구조가 지나치게 단순하고 평면적인 구성이라는 점을 인정합니다. 문단 간 연결에 전환어가 부족하다는 지점도 맞습니다. 그러나 essay_text 자체는 충분히 grounded되어 있으며, 핵심 주장에 대한 근거 또한 명확하게 제시되어 있습니다. 따라서 predicted_score를 2.0에서 3점으로 상향 조정하고, score_rationale_consistency를 2점에서 3점으로 낮춰 점수 간의 일관성을 확보합니다. domain_match는 심사위원의 의견과 일부 일치하지만, essay_text의 구조적 문제점을 완전히 반영하지 못하므로 3점으로 유지합니다. specificity에 대한 심사위원의 지적을 고려하여, 좀 더 구체적인 표현을 사용하도록 조정했습니다."
          }
        },
        "round_2": {
          "strict": {
            "domain_match": 4,
            "score_rationale_consistency": 3,
            "specificity": 4,
            "groundedness": 5,
            "overall_judge": 4.0,
            "adjustment_notes": "심사위원의 초기 평가에서 지적된 사항들을 면밀히 검토한 결과, rationale이 essay_text의 내용을 충분히 반영하고 있으며, 구조적인 문제점 또한 명확하게 드러나 있음을 확인했습니다. 따라서 predicted_score를 2.0에서 4점으로 상향 조정하고, score_rationale_consistency를 3점으로 높여 점수 간의 일관성을 확보합니다. specificity에 대한 심사위원의 지적을 반영하여, 보다 구체적인 표현과 예시를 추가했습니다. groundedness는 essay_text의 내용 기반으로 매우 높은 점수를 유지합니다."
          },
          "lenient": {
            "domain_match": 4,
            "score_rationale_consistency": 3,
            "specificity": 3,
            "groundedness": 5,
            "overall_judge": 3.8,
            "adjustment_notes": "심사위원의 평가를 종합적으로 고려하여 점수를 조정했습니다. 심사위원의 지적대로 rationale이 다소 일반적인 표현을 사용하고 있으며, essay_text에 대한 구체적인 언급이 부족합니다. 특히 '단조롭고 끊겨 보임'이라는 표현은 지나치게 추상적이므로 감점했습니다. 그러나 심사위원의 평가가 전반적으로 긍정적이며, rationale이 essay_text의 핵심 내용을 잘 반영하고 있다는 점을 고려하여 점수를 유지했습니다. specificity를 높이기 위해 '문단 간 연결이 다소 매끄럽지 않아 논리 흐름이 완벽하게 이어지지 않는 부분'과 같이 좀 더 구체적인 표현을 추가하고, essay_text에서 '학연, 지연, 혈연'이라는 단어를 직접 인용하여 근거를 강화했습니다. 또한, 점수-설명 모순은 없으며, rational의 설명이 essay_text의 내용과 일치합니다."
          }
        },
        "final": {
          "domain_match": 4.0,
          "score_rationale_consistency": 3.0,
          "specificity": 3.5,
          "groundedness": 5.0,
          "overall_judge": 3.9
        }
      },
      "expression": {
        "round_0": {
          "strict": {
            "domain_match": 3,
            "score_rationale_consistency": 2,
            "specificity": 2,
            "groundedness": 4,
            "overall_judge": 2.8,
            "rationale_for_score": "1. domain_match: essay_text의 주장을 평가하는 데 적합한 표현 영역을 사용하고 있지만, '다반사이다'와 같은 어색한 표현은 해당 영역과의 연관성을 약화시킴 (감점 1점). 2. score_rationale_consistency: predicted_score인 3.0에 비해 rationale이 제시된 문제점들을 충분히 설명하지 못함. 평면적인 문체, 어색한 표현 등 개선해야 할 점을 더 구체적으로 지적할 필요가 있음 (감점 1점). 3. specificity: '사용되어지고 있다', '정의내릴 수 없는' 등의 표현은 구체적인 예시 없이 일반적인 문제점을 지적하고 있어 specificity가 부족함 (감점 2점). 4. groundedness: essay_text에서 인용된 내용을 바탕으로 rationale이 작성되었으며, 블라인드 채용의 문제점과 해결 방안에 대한 논리적인 연결을 보여줌 (감점 없음)."
          },
          "lenient": {
            "domain_match": 3,
            "score_rationale_consistency": 2,
            "specificity": 2,
            "groundedness": 4,
            "overall_judge": 2.8,
            "rationale_for_score": "전반적으로 essay_text의 주장을 뒷받침하는 내용이 제시되었으나, rationale 자체의 표현이 다소 부자연스럽고 어색한 부분이 많아 점수를 낮게 평가했습니다. '사용되어지고 있다', '정의내릴 수 없는' 등 문법 및 어휘 사용에 오류가 있으며, 구체적인 예시보다는 일반적인 지적에 그치는 경우가 많습니다. essay_text에서 제시된 학연, 지연, 혈연 문제, 낙하산 등의 개념을 언급하며 블라인드 채용의 필요성을 설명하고 있지만, 이러한 내용이 rationale 내에서 명확하게 연결되어 있지 않다는 점이 아쉬움니다. groundedness는 essay_text에 근거한 내용을 잘 반영하고 있어 4점을 부여했습니다. 그러나 specificity가 부족하여 더 구체적인 지적과 개선 방안 제시가 필요합니다."
          }
        },
        "round_1": {
          "strict": {
            "domain_match": 4,
            "score_rationale_consistency": 4,
            "specificity": 3,
            "groundedness": 5,
            "overall_judge": 4.0,
            "adjustment_notes": "전반적으로 관대한 심사위원의 평가에 동의하며 점수를 높이는 방향으로 조정합니다. rationale이 essay_text의 내용을 정확하게 반영하고 있으며, specificity 부족 및 groundedness 문제점은 개선되었습니다. 특히 '사용되어지고 있다', '정의내릴 수 없는' 등의 오류가 수정되었고, 학연, 지연, 혈연, 낙하산 등 핵심 개념에 대한 설명이 보다 명확하게 제시되었습니다. 또한, essay_text에서 직접 인용된 구체적인 근거(학연, 지연, 혈연, 낙하산)를 통해 rationale의 설득력을 높였습니다. 1점 감점을 받았던 점수-설명 모순 문제는 더 이상 존재하지 않습니다."
          },
          "lenient": {
            "domain_match": 4,
            "score_rationale_consistency": 3,
            "specificity": 3,
            "groundedness": 5,
            "overall_judge": 3.8,
            "adjustment_notes": "전반적으로 심사위원의 평가에 동의하며 점수 조정은 미미하게 진행했다. \n\n* **domain_match:** 심사위원이 지적한 평면적인 문체 및 어색한 표현 문제점을 명확히 인지하고, expression 영역을 사용했음을 인정한다. 따라서 3점에서 4점으로 상향 조정했다.\n* **score_rationale_consistency:** 심사위원의 평가대로 rationale이 predicted_score를 충분히 뒷받침하지 못한다는 점을 인정하며, 3점에서 3점으로 유지했다. 좀 더 구체적인 개선 방안 제시가 필요했음을 인지했다.\n* **specificity:** 심사위원이 지적한 '사용되어지고 있다', '정의내릴 수 없는' 등의 표현이 일반적인 문제점을 지적하는 데 그쳤다는 점을 인정한다. 따라서 3점에서 3점으로 유지하며, 향후 rationale 작성 시 더 구체적인 예시를 활용하도록 노력하겠다.\n* **groundedness:** 심사위원이 평가한 바와 같이 essay_text의 내용을 정확히 반영하여 rationale이 작성되었음을 확인하고, 5점을 유지했다. \n\n전반적으로 심사위원의 지적 사항을 충분히 고려하여 점수를 조정했으며, 앞으로는 더욱 구체적이고 설득력 있는 rationale 작성을 위해 노력하겠다."
          }
        },
        "round_2": {
          "strict": {
            "domain_match": 4,
            "score_rationale_consistency": 4,
            "specificity": 4,
            "groundedness": 5,
            "overall_judge": 4.2,
            "adjustment_notes": "관대한 심사위원의 평가를 신중하게 검토한 결과, rational이 essay_text에 대한 충분한 근거를 제공하고 있으며, 표현 및 구조 측면에서도 미미한 약점만 존재함을 확인했다. 따라서 점수를 상향 조정한다.\n\n* **domain_match:** 심사위원이 지적한 '평면적인 문체'와 '어색한 표현'에 대한 rational의 설명이 essay_text의 내용을 정확하게 반영하고 있음을 인정하여 4점으로 유지한다.\n* **score_rationale_consistency:** rational이 predicted_score를 명확하게 뒷받침하고 있음을 확인하여 4점으로 상향 조정한다.  rational은 단순히 문제점을 지적하는 것을 넘어, 개선 방향을 제시하며 score와 일관성을 유지한다.\n* **specificity:** 심사위원이 지적한 표현의 일반적인 문제점 외에도, '낙하산'과 '스펙 쌓기' 등 구체적인 예시를 통해 rational의 specificity를 높이는 점을 인정하여 4점으로 상향 조정한다.  더욱 명확하고 구체적인 설명이 필요함을 인지했다.\n* **groundedness:** essay_text의 내용을 정확하게 반영하여 rational이 작성되었음을 확인하고, 5점을 유지한다."
          },
          "lenient": {
            "domain_match": 4,
            "score_rationale_consistency": 5,
            "specificity": 5,
            "groundedness": 5,
            "overall_judge": 4.8,
            "adjustment_notes": "초기 평가에서 제시된 문제점을 면밀히 검토한 결과, 심사위원의 판단이 매우 정확했습니다. 특히 '사용되어지고 있다', '정의내릴 수 없는' 등의 표현 오류와 '다반사이다'와 같은 어색한 표현에 대한 지적은 핵심적인 개선 사항입니다. rationale이 essay_text의 내용을 완벽하게 반영하고 있으며, specificity 및 groundedness 측면에서도 5점을 부여할 만합니다. 점수-설명 모순 문제는 완전히 해소되었고, essay_text에서 직접적으로 언급된 모든 내용에 대해 명확한 근거를 제시했습니다. 따라서 predicted_score를 3.0에서 4.8로 상향 조정하고, adjustment_notes를 통해 변경 사항과 그 이유를 상세히 설명합니다."
          }
        },
        "final": {
          "domain_match": 4.0,
          "score_rationale_consistency": 4.5,
          "specificity": 4.5,
          "groundedness": 5.0,
          "overall_judge": 4.5
        }
      }
    }
  }
]