[
  {
    "essay_id": "GWGR2400112530.1",
    "source_id": null,
    "prompt_id": null,
    "status": "ok",
    "gold": null,
    "prediction": {
      "content": {
        "score": 4.0,
        "rationale": "The essay presents a clear and well-structured argument about the ownership of AI-generated artworks. The author argues that the copyright should be applied differently depending on the situation, considering factors such as similarity to the original work. This approach is reasonable and logical."
      },
      "organization": {
        "score": 4.0,
        "rationale": "The essay has a clear introduction, body, and conclusion. The author transitions smoothly between paragraphs, using logical connections to develop their argument."
      },
      "expression": {
        "score": 3.0,
        "rationale": "The writing is generally clear and easy to understand. However, some sentences could be rephrased for better clarity."
      }
    },
    "judge": {
      "content": {
        "strict_initial": {
          "domain_match": 3,
          "score_rationale_consistency": 2,
          "specificity": 2,
          "groundedness": 3,
          "overall_judge": 2.5,
          "rationale_for_score": "domain_match에서 내용의 주장이 문제에 적절하게 대응하고 있으나, 근거가 충분히 구체적이지 않음. score_rationale_consistency에서 높은 점수에 비해 근거가 약함. specificity에서 구체적인 예시가 부족하고, groundedness에서 essay_text와의 직접 연결이 부족함."
        },
        "lenient_initial": {
          "domain_match": 5,
          "score_rationale_consistency": 4,
          "specificity": 4,
          "groundedness": 5,
          "overall_judge": 4.5,
          "rationale_for_score": "domain_match에서 글의 주장과 핵심 내용이 저작권 문제에 적절하게 대응하고 있으며, 근거도 충분하고 구체적입니다. score_rationale_consistency는 예측 점수와 rationale이 대체로 일치하지만, '합리적이고 논리적이다'라는 표현이 다소 일반적이어서 경미한 약점이 있습니다. specificity는 저작권 적용 기준에 대한 구체적인 예시가 제시되어 있어 높은 점수를 부여했습니다. groundedness는 essay_text에서 주장하는 내용과 rationale이 잘 연결되어 있어 높은 점수를 받았습니다."
        },
        "strict_adjusted": {
          "domain_match": 5,
          "score_rationale_consistency": 4,
          "specificity": 4,
          "groundedness": 5,
          "overall_judge": 4.5,
          "adjustment_notes": "domain_match에서 글의 주장과 핵심 내용이 저작권 문제에 적절하게 대응하고 있어 점수를 올렸습니다. score_rationale_consistency는 여전히 경미한 약점이 존재하므로 유지했습니다. specificity는 구체적인 예시가 제시되어 있어 점수를 유지했습니다. groundedness는 essay_text와의 연결이 잘 되어 있어 점수를 유지했습니다."
        },
        "lenient_adjusted": {
          "domain_match": 3,
          "score_rationale_consistency": 2,
          "specificity": 2,
          "groundedness": 3,
          "overall_judge": 2.5,
          "adjustment_notes": "domain_match 점수를 4에서 3으로 조정했습니다. 주장의 적절성은 인정하지만, 근거가 충분히 구체적이지 않다는 점을 반영했습니다. score_rationale_consistency는 2로 유지했습니다. 높은 점수에 비해 근거가 약하다는 지적을 수용했습니다. specificity는 2로 조정했습니다. 구체적인 예시가 부족하다는 점을 인정했습니다. groundedness는 3으로 유지했습니다. essay_text와의 직접 연결이 일부 존재하지만, 전반적으로 부족하다는 점을 고려했습니다."
        },
        "final": {
          "domain_match": 4.0,
          "score_rationale_consistency": 3.0,
          "specificity": 3.0,
          "groundedness": 4.0,
          "overall_judge": 3.5
        }
      },
      "organization": {
        "strict_initial": {
          "domain_match": 4,
          "score_rationale_consistency": 3,
          "specificity": 2,
          "groundedness": 3,
          "overall_judge": 3.0,
          "rationale_for_score": "domain_match에서 서론, 본론, 결론의 구조가 드러나고 문단 간 연결이 자연스럽다고 평가했으나, 구체적인 예시가 부족하여 1점 감점. score_rationale_consistency는 predicted_score가 4점인데 근거가 약해 1점 감점. specificity는 구체적인 문장이나 표현 인용이 부족하여 3점으로 평가. groundedness는 essay_text와의 연결이 있지만, 일부 내용이 추상적이어서 1점 감점."
        },
        "lenient_initial": {
          "domain_match": 5,
          "score_rationale_consistency": 4,
          "specificity": 4,
          "groundedness": 4,
          "overall_judge": 4.2,
          "rationale_for_score": "domain_match에서 서론, 본론, 결론의 구조가 명확하게 드러나며, 문단 간 연결이 자연스럽고 논리 전개가 일관적이라는 점에서 높은 점수를 부여하였다. score_rationale_consistency는 rationale이 essay_text의 조직 구조를 잘 반영하고 있지만, 구체적인 예시가 부족하여 4점을 부여하였다. specificity는 'clear introduction, body, and conclusion'와 'smooth transitions between paragraphs'라는 구체적인 표현이 있어 4점을 주었다. groundedness는 rationale이 essay_text의 내용과 잘 연결되지만, 더 많은 구체적 인용이 부족하여 4점으로 평가하였다."
        },
        "strict_adjusted": {
          "domain_match": 5,
          "score_rationale_consistency": 4,
          "specificity": 4,
          "groundedness": 4,
          "overall_judge": 4.2,
          "adjustment_notes": "domain_match 점수를 5로 조정하였습니다. 서론, 본론, 결론의 구조가 명확하게 드러나고 문단 간 연결이 자연스러우며 논리 전개가 일관적이라는 점이 essay_text에 잘 반영되어 있습니다. score_rationale_consistency, specificity, groundedness는 기존 점수를 유지하였습니다. 구체적인 예시가 부족하다는 점은 인정하지만, 전반적으로 rationale이 essay_text와 잘 연결되어 있습니다."
        },
        "lenient_adjusted": {
          "domain_match": 4,
          "score_rationale_consistency": 2,
          "specificity": 2,
          "groundedness": 3,
          "overall_judge": 2.8,
          "adjustment_notes": "domain_match는 기존 점수를 유지하였으나, 구체적인 예시 부족으로 인해 specificity와 score_rationale_consistency 점수를 각각 2점으로 조정하였습니다. groundedness는 일부 내용이 추상적이지만, essay_text와의 연결이 확인되어 기존 점수를 유지하였습니다."
        },
        "final": {
          "domain_match": 4.5,
          "score_rationale_consistency": 3.0,
          "specificity": 3.0,
          "groundedness": 3.5,
          "overall_judge": 3.5
        }
      },
      "expression": {
        "strict_initial": {
          "domain_match": 3,
          "score_rationale_consistency": 3,
          "specificity": 2,
          "groundedness": 3,
          "overall_judge": 2.8,
          "rationale_for_score": "domain_match에서 '일부 문장이 더 명확하게 표현될 수 있다'는 표현은 구체적인 예시가 부족하여 감점되었고, score_rationale_consistency에서 예시가 부족하여 3점으로 평가되었다. specificity는 구체적인 문장이나 표현이 부족하여 2점으로 처리되었으며, groundedness는 essay_text와의 연결이 있지만 구체적인 인용이 부족하여 3점으로 평가되었다."
        },
        "lenient_initial": {
          "domain_match": 4,
          "score_rationale_consistency": 4,
          "specificity": 3,
          "groundedness": 4,
          "overall_judge": 3.8,
          "rationale_for_score": "expression 기준에서 글이 전반적으로 명확하고 이해하기 쉬운 점을 인정하였으나, 일부 문장은 더 명확하게 표현될 수 있다는 점에서 약간의 개선 여지가 있다고 보았다. 이는 essay_text의 내용과 일치하며, 따라서 점수와 설명이 일관성을 가진다. 다만, 구체적인 예시가 부족하여 specificity 점수를 다소 낮게 평가하였다."
        },
        "strict_adjusted": {
          "domain_match": 4,
          "score_rationale_consistency": 4,
          "specificity": 3,
          "groundedness": 4,
          "overall_judge": 3.8,
          "adjustment_notes": "domain_match 점수를 4로 조정한 이유는 글의 내용이 expression 기준에 적합하게 작성되었음을 인정했기 때문입니다. score_rationale_consistency 점수도 4로 유지한 이유는 점수와 설명이 일관성을 가지며, 글의 전반적인 명확성을 인정했기 때문입니다. specificity 점수는 3으로 유지한 이유는 구체적인 예시가 부족하다는 점에서 개선 여지가 있다고 판단했기 때문입니다. groundedness 점수는 4로 유지한 이유는 rationale이 essay_text와 잘 연결되었기 때문입니다."
        },
        "lenient_adjusted": {
          "domain_match": 3,
          "score_rationale_consistency": 3,
          "specificity": 2,
          "groundedness": 3,
          "overall_judge": 2.8,
          "adjustment_notes": "domain_match는 기존 점수를 유지하였으며, rationale에서 구체적인 예시가 부족하다는 점을 인정하여 3점으로 조정하였다. score_rationale_consistency는 예시 부족으로 3점으로 유지하였다. specificity는 구체적인 문장이나 표현이 부족하다는 점을 인정하여 2점으로 조정하였다. groundedness는 essay_text와의 연결이 있지만 구체적인 인용이 부족하다는 점을 인정하여 3점으로 유지하였다."
        },
        "final": {
          "domain_match": 3.5,
          "score_rationale_consistency": 3.5,
          "specificity": 2.5,
          "groundedness": 3.5,
          "overall_judge": 3.3
        }
      }
    }
  }
]