{
  "context": "GWGR2400107470.1_expression_r3_lenient_text_only",
  "raw_response": "{\n  \"domain_match\": 5,\n  \"score_rationale_consistency\": 2,\n  \"specificity\": 2,\n  \"groundedness\": 5,\n  \"overall_judge\": 3.0,\n  \"adjustment_notes\": \"1) domain_match: rationale 이 expression(자연스러움, 어휘 다양성 등) 기준을 명확히 적용했으므로 기존 점수 유지 (5점). 2) score_rationale_consistency: predicted_score 4.0 은 '경미한 약점' 존재를 전제로 하므로, rationale 이 지적한 '어색한 표현'과 '어휘 다양성 부족'이 이를 정당화하므로 기존 점수 유지 (4점). 3) specificity: 관대한 심사위원의 평가에 동의함. '어색하게 느껴질 수 있다', '다양성을 추구할 수 있다'는 구체적인 문장이나 예시 없이 일반적 평가를 한 것으로, 구체성이 부족하여 감점 (4→2점). 4) groundedness: 지적된 문제점이 essay_text 의 내용과 맥락상 타당하므로 허구가 없음을 인정하여 기존 점수 유지 (5점).\""
}