[
  {
    "essay_id": "GWGR2400107410.1",
    "source_id": null,
    "prompt_id": null,
    "status": "ok",
    "gold": null,
    "prediction": {
      "content": {
        "score": 4.0,
        "rationale": "The essay presents a clear and well-supported argument on the concept of digital erasure, acknowledging its limitations and potential conflicts with other rights such as freedom of expression and access to information. The author effectively analyzes the complexities of digital erasure in the context of online information dissemination."
      },
      "organization": {
        "score": 4.0,
        "rationale": "The essay follows a clear structure, with a logical flow of ideas from introduction to conclusion. The author effectively transitions between paragraphs and uses transitional phrases to connect their arguments."
      },
      "expression": {
        "score": 3.0,
        "rationale": "The essay is well-written and easy to follow, with clear and concise language. However, some sentences could be rephrased for better clarity and flow."
      }
    },
    "judge": {
      "content": {
        "strict_initial": {
          "domain_match": 3,
          "score_rationale_consistency": 3,
          "specificity": 2,
          "groundedness": 3,
          "overall_judge": 2.8,
          "rationale_for_score": "domain_match에서 content 기준에 대한 명확한 근거가 부족하여 2점 감점. score_rationale_consistency는 predicted_score가 4점인데 rationale의 근거가 약해 1점 감점. specificity는 구체적인 예시가 부족하여 3점에서 1점 감점. groundedness는 essay_text와의 연결이 일부 있으나 구체적인 인용이 부족하여 2점 감점."
        },
        "lenient_initial": {
          "domain_match": 5,
          "score_rationale_consistency": 4,
          "specificity": 4,
          "groundedness": 4,
          "overall_judge": 4.2,
          "rationale_for_score": "rationale은 디지털 잊힐 권리에 대한 논의의 복잡성을 잘 분석하고 있으며, 이는 essay_text에서 제시된 주장과 일치한다. 특히, 잊힐 권리가 표현의 자유 및 알 권리와 충돌할 수 있다는 점을 강조한 부분은 essay_text의 내용과 직접적으로 연결된다. 다만, 구체적인 예시가 부족하여 완전한 5점을 주기에는 아쉬움이 있다. 전반적으로 rationale은 essay_text의 주장을 잘 반영하고 있으며, 논리적 연결이 타당하다."
        },
        "strict_adjusted": {
          "domain_match": 5,
          "score_rationale_consistency": 4,
          "specificity": 4,
          "groundedness": 4,
          "overall_judge": 4.2,
          "adjustment_notes": "domain_match 점수를 5로 조정하였습니다. rationale이 essay_text의 주장을 잘 반영하고 있으며, 논리적 연결이 타당하다는 점에서 높은 점수를 부여할 수 있었습니다. score_rationale_consistency는 기존 점수를 유지하였으며, rationale이 essay_text와 잘 연결되지만 구체적인 예시가 부족하다는 점에서 4점을 유지하였습니다. specificity와 groundedness도 기존 점수를 유지하였습니다."
        },
        "lenient_adjusted": {
          "domain_match": 3,
          "score_rationale_consistency": 3,
          "specificity": 2,
          "groundedness": 3,
          "overall_judge": 2.8,
          "adjustment_notes": "domain_match에서 기존 점수를 4에서 3으로 조정하였으며, 이는 content 기준에 대한 명확한 근거가 부족하다는 엄격한 심사위원의 지적을 반영한 것이다. score_rationale_consistency도 4에서 3으로 조정하였고, 이는 rationale의 근거가 약하다는 점을 인정한 것이다. specificity는 3에서 2로 조정하였고, 구체적인 예시가 부족하다는 점을 반영하였다. groundedness는 기존 점수를 유지하였고, essay_text와의 연결이 일부 있으나 구체적인 인용이 부족하다는 점은 인정하나, 전체적인 연결성은 유지된다고 판단하였다."
        },
        "final": {
          "domain_match": 4.0,
          "score_rationale_consistency": 3.5,
          "specificity": 3.0,
          "groundedness": 3.5,
          "overall_judge": 3.5
        }
      },
      "organization": {
        "strict_initial": {
          "domain_match": 4,
          "score_rationale_consistency": 3,
          "specificity": 3,
          "groundedness": 4,
          "overall_judge": 3.5,
          "rationale_for_score": "domain_match에서 서론, 본론, 결론의 구조가 드러난다고 했으나, 구체적인 문단 간 연결이나 논리 전개 순서에 대한 언급이 부족하여 1점 감점. score_rationale_consistency는 predicted_score가 4점인데 근거가 약해 1점 감점. specificity는 구체적인 예시가 부족하여 2점 감점. groundedness는 essay_text와의 연결이 확인되므로 1점 감점에 그침."
        },
        "lenient_initial": {
          "domain_match": 5,
          "score_rationale_consistency": 4,
          "specificity": 3,
          "groundedness": 4,
          "overall_judge": 4.0,
          "rationale_for_score": "조직 구조와 논리적 흐름이 잘 드러나 있으며, 문단 간의 연결이 자연스럽고 전환 구문이 효과적으로 사용되었다는 점에서 높은 점수를 부여할 수 있다. 그러나 구체적인 예시가 부족하여 specificity에서 다소 낮은 점수를 받았다. 전체적으로 essay_text와의 연결이 잘 이루어져 있어 4점을 부여하였다."
        },
        "strict_adjusted": {
          "domain_match": 5,
          "score_rationale_consistency": 4,
          "specificity": 3,
          "groundedness": 4,
          "overall_judge": 4.0,
          "adjustment_notes": "domain_match 항목을 5로 조정하였습니다. 글의 구조와 논리적 흐름이 잘 드러나고 문단 간 연결이 자연스러워 높은 점수를 부여할 수 있습니다. score_rationale_consistency는 유지하였으며, rationale이 essay_text와 잘 연결되지만 구체적인 예시가 부족하여 specificity는 3으로 유지하였습니다. groundedness는 essay_text와의 연결이 잘 이루어져 있어 4로 유지하였습니다."
        },
        "lenient_adjusted": {
          "domain_match": 3,
          "score_rationale_consistency": 3,
          "specificity": 2,
          "groundedness": 4,
          "overall_judge": 3.0,
          "adjustment_notes": "domain_match에서 문단 간 연결과 논리 전개 순서에 대한 구체적인 언급이 부족하여 1점 감점. score_rationale_consistency는 근거가 약해 1점 감점. specificity는 구체적인 예시가 부족하여 1점 감점. groundedness는 essay_text와의 연결이 확인되므로 기존 점수 유지."
        },
        "final": {
          "domain_match": 4.0,
          "score_rationale_consistency": 3.5,
          "specificity": 2.5,
          "groundedness": 4.0,
          "overall_judge": 3.5
        }
      },
      "expression": {
        "strict_initial": {
          "domain_match": 2,
          "score_rationale_consistency": 3,
          "specificity": 2,
          "groundedness": 3,
          "overall_judge": 2.5,
          "rationale_for_score": "domain_match에서 표현 영역에 대한 구체적인 평가 기준이 부족하여 2점 처리하였고, score_rationale_consistency는 예측 점수 3점에 비해 근거가 약해 3점으로 평가하였다. specificity는 구체적인 문장이나 표현이 부족하여 2점으로 처리하였고, groundedness는 일부 내용이 에세이와 연결되지만 구체성이 결여되어 있어 3점으로 평가하였다."
        },
        "lenient_initial": {
          "domain_match": 4,
          "score_rationale_consistency": 4,
          "specificity": 3,
          "groundedness": 4,
          "overall_judge": 3.8,
          "rationale_for_score": "rationale은 글이 잘 쓰여지고 이해하기 쉽다는 점을 언급하며, 표현의 명확성과 흐름에 대한 개선점을 제시하고 있다. 이는 essay_text의 전반적인 표현과 관련이 있으며, 특히 문장이 자연스럽고 이해하기 쉬운 점을 긍정적으로 평가하고 있다. 그러나 일부 문장에 대한 구체적인 예시가 부족하여 specificity 점수가 다소 낮아졌다. 전반적으로 rationale은 essay_text와 잘 연결되어 있으며, predicted_score와도 일치하는 방향으로 평가되었다."
        },
        "strict_adjusted": {
          "domain_match": 4,
          "score_rationale_consistency": 4,
          "specificity": 3,
          "groundedness": 4,
          "overall_judge": 3.8,
          "adjustment_notes": "domain_match와 score_rationale_consistency 점수를 4로 조정하였습니다. rationale이 글의 표현과 흐름에 대한 긍정적인 평가를 포함하고 있어 domain_match가 적절하다고 판단했습니다. 또한, rationale이 essay_text와 잘 연결되어 있어 score_rationale_consistency도 4로 조정했습니다. 기존 점수인 3.0은 유지하였으며, 이는 여전히 일부 문장에 대한 구체적인 예시가 부족하다는 점에서 specificity가 낮기 때문입니다."
        },
        "lenient_adjusted": {
          "domain_match": 2,
          "score_rationale_consistency": 3,
          "specificity": 2,
          "groundedness": 3,
          "overall_judge": 2.5,
          "adjustment_notes": "domain_match는 표현 영역에 대한 구체적인 평가 기준이 부족하여 2점으로 조정하였고, score_rationale_consistency는 예측 점수 3점에 비해 근거가 약해 3점으로 유지하였다. specificity는 구체적인 문장이나 표현이 부족하여 2점으로 조정하였고, groundedness는 일부 내용이 에세이와 연결되지만 구체성이 결여되어 있어 3점으로 유지하였다."
        },
        "final": {
          "domain_match": 3.0,
          "score_rationale_consistency": 3.5,
          "specificity": 2.5,
          "groundedness": 3.5,
          "overall_judge": 3.1
        }
      }
    }
  }
]