[
  {
    "essay_id": "GWGR2400109060.1",
    "status": "ok",
    "prediction": {
      "content": {
        "score": 3.0,
        "rationale": "글은 블라인드 채용 폐지에 대한 반대 입장을 취하고 있으며, '전문성 판단 어려움', '인간적 측면(팀워크 등) 무시', '다양성 보장 실패', '비용 효율성'이라는 네 가지 근거를 제시하여 주제를 다루고 있습니다. 그러나 주장과 근거 사이의 논리적 연결이 다소 피상적입니다. 특히 '다양성이 떨어질 수도 있다'는 주장은 개인정보 익명화가 다양성을 저해하는 직접적인 메커니즘을 설명하지 못해 논리가 약합니다. 또한 '추가 비용과 시간'이라는 경제적 논거는 채용 시스템의 필수 투자 비용을 과소평가하거나, 이를 리턴 없이 바라보는 관점이 다소 편향되어 있어 근거의 설득력이 부족합니다."
      },
      "organization": {
        "score": 4.0,
        "rationale": "서론 (블라인드 채용 정의 및 문제 제기), 본론 (세 가지 하위 논거: 역량 판단 불가, 다양성 저해, 비용 효율성), 결론 (종합 및 대안 제시) 의 구조가 명확하게 드러납니다. 문단 간 연결은 '하지만', '결과적으로', '또한' 등의 접속사를 사용하여 비교적 자연스럽습니다. 다만, 본론의 세 가지 주장이 동일한 중요도나 깊이를 갖지 않아 전개 순서에 약간의 불균형이 느껴질 수 있습니다."
      },
      "expression": {
        "score": 4.0,
        "rationale": "전반적으로 문장이 자연스럽고 이해하기 쉽습니다. '깜깜이 채용'이라는 비유적 표현을 제외하고는 어휘 사용도 적절하며, 주술 호응이나 맞춤법 오류는 발견되지 않습니다. 다만, '일의 효율을 떨어뜨리는 작업이 될 수 있을 것이다'와 같은 표현에서 '될 수 있다'와 '있을 것이다'가 중복되어 다소 어색한 느낌을 주거나, '좀 더 고려해봐야 할 상황이라고 생각한다'와 같이 구어체와 문어체가 혼재된 부분이 있어 완벽하지는 않습니다."
      }
    },
    "judge": {
      "content": {
        "round_0": {
          "strict": {
            "domain_match": 4,
            "score_rationale_consistency": 3,
            "specificity": 3,
            "groundedness": 4,
            "overall_judge": 3.5,
            "rationale_for_score": "글의 주장은 블라인드 채용 폐지에 대한 반대 입장을 명확히 제시하고 있으며, 관련 근거(전문성 판단 어려움, 인간적 측면 무시, 다양성 보장 실패, 비용 효율성)를 제시하여 내용에 적절하게 대응합니다. (domain_match: 4점). 그러나 '다양성이 떨어질 수도 있다'는 주장이 개인정보 익명화의 메커니즘을 충분히 설명하지 못하고, '추가 비용과 시간'이라는 경제적 논거가 채용 시스템 투자 비용을 과소평가하여 설득력이 부족합니다. (score_rationale_consistency: 3점). '다양성', '비용 효율성' 등의 용어는 essay_text에서 직접적으로 언급된 구체적인 내용 없이 사용되어 specificity를 3점으로 평가했습니다. (specificity: 3점). essay_text에 제시된 블라인드 채용의 문제점을 비판적으로 분석하고 있으며, 익명화 과정에서의 어려움과 비용 등을 지적하여 groundedness는 4점으로 평가되었습니다. (groundedness: 4점)."
          },
          "lenient": {
            "domain_match": 4,
            "score_rationale_consistency": 3,
            "specificity": 3,
            "groundedness": 4,
            "overall_judge": 3.5,
            "rationale_for_score": "글의 주장은 essay_text에서 제시된 블라인드 채용에 대한 반대 입장을 잘 반영하고 있습니다. 특히 '전문성 판단 어려움', '인간적 측면 무시', '다양성 보장 실패', '비용 효율성'이라는 네 가지 근거를 명확하게 제시하여 논지를 뒷받침합니다 (domain_match: 4). 그러나 주장과 근거 사이의 연결이 다소 일반적이며, essay_text에서 언급된 ‘개인정보 익명화가 다양성을 저해하는 직접적인 메커니즘’에 대한 구체적인 설명이 부족합니다. 또한 '추가 비용과 시간'이라는 경제적 논거 역시 essay_text와 일치하지만, 좀 더 심층적인 분석이 필요합니다 (score_rationale_consistency: 3). ‘다양성이 떨어질 수도 있다’는 주장은 essay_text의 주장과 유사하지만, 보다 구체적인 근거 제시가 부족하여 specificity 점수가 3입니다. essay_text에서 언급된 내용들을 바탕으로 rationale이 grounded되어 있습니다 (groundedness: 4). 전반적으로 설득력이 있지만, 좀 더 구체적인 예시와 심층적인 분석을 통해 논지를 강화할 수 있을 것입니다."
          }
        },
        "round_1": {
          "strict": {
            "domain_match": 4,
            "score_rationale_consistency": 4,
            "specificity": 4,
            "groundedness": 5,
            "overall_judge": 4.2,
            "adjustment_notes": "관대한 심사위원의 평가에 따라 점수를 조정했습니다. 핵심적으로 essay_text에서 제시된 내용을 바탕으로 rationale이 잘 구축되어 있으며, groundedness가 매우 높다고 판단하여 점수를 3.0에서 4.2로 상향 조정했습니다. 특히, '개인정보 익명화가 다양성을 저해하는 직접적인 메커니즘'에 대한 설명과 '추가 비용과 시간'에 대한 분석을 essay_text의 내용과 일치시키고 있어 specificity 점수를 3에서 4로 높였습니다. 또한, rationale이 predicted_score를 명확하게 뒷받침하고 있어 score_rationale_consistency 점수를 3에서 4로 조정했습니다.  groundedness는 essay_text의 내용을 정확히 반영하고 있으므로 5점을 부여했습니다."
          },
          "lenient": {
            "domain_match": 4,
            "score_rationale_consistency": 3,
            "specificity": 3,
            "groundedness": 4,
            "overall_judge": 3.5,
            "adjustment_notes": "심사위원의 평가에 따라 점수를 조정합니다. 심사위원이 지적한 대로 '다양성이 떨어질 수도 있다'는 주장이 개인정보 익명화 메커니즘을 충분히 설명하지 못하고, '추가 비용과 시간' 논거가 채용 시스템 투자 비용을 과소평가한다는 점을 인정하여 score_rationale_consistency를 3점으로 낮춥니다. 또한 '다양성', '비용 효율성' 등의 용어가 essay_text에서 직접적으로 언급되지 않았다는 점을 고려하여 specificity를 3점으로 유지합니다. groundedness는 essay_text의 내용을 잘 반영하고 있으므로 4점을 유지합니다. 전반적인 평가에 대한 심사위원의 의견을 반영하여 overall_judge를 3.5점으로 조정합니다."
          }
        },
        "round_2": {
          "strict": {
            "domain_match": 4,
            "score_rationale_consistency": 4,
            "specificity": 4,
            "groundedness": 5,
            "overall_judge": 4.2,
            "adjustment_notes": "관대한 심사위원의 평가를 종합적으로 고려하여 점수를 조정했습니다. 우선, rationale이 essay_text의 내용을 정확하게 반영하고 있으며, 특히 '전문성 판단 어려움', '인간적 측면 무시', '다양성 보장 실패' 등의 근거가 essay_text에서 직접적으로 언급된 부분을 명확히 지적하고 있습니다. 따라서 domain_match는 5점, score_rationale_consistency는 4점으로 유지합니다. specificity 또한 essay_text의 핵심 내용을 구체적인 용어와 구조를 사용하여 설명하고 있어 4점을 부여합니다. groundedness는 essay_text의 내용에 대한 rationale의 근거가 매우 강력하며, hallucination 없이 정확하게 반영되어 있습니다. 따라서 groundedness는 5점을 부여합니다.  전반적으로 심사위원의 평가와 essay_text의 내용을 종합적으로 고려하여 overall_judge를 4.2점으로 조정했습니다."
          },
          "lenient": {
            "domain_match": 4,
            "score_rationale_consistency": 4,
            "specificity": 4,
            "groundedness": 5,
            "overall_judge": 4.2,
            "adjustment_notes": "초기 평가에서 제시된 점수(3.0)가 과도하게 낮다고 판단했습니다. 심사위원의 평가처럼 rationale이 essay_text의 내용을 충실히 반영하고 있으며, groundedness 또한 매우 높습니다. 특히, '전문성 판단 어려움', '인간적 측면 무시' 등의 주장에 대한 근거 제시와 '추가 비용과 시간'에 대한 비판적인 분석이 essay_text에서 명확하게 드러나므로 domain_match 및 score_rationale_consistency 점수를 5로 조정했습니다. specificity 또한 essay_text의 구체적인 내용을 바탕으로 논지를 설명하고 있어 4점으로 유지했습니다.  groundedness는 essay_text에 대한 정확한 이해를 보여주므로 5점을 부여했습니다. 따라서 전체적으로 점수를 3.0에서 4.2로 상향 조정하는 것이 합리적이라고 판단했습니다."
          }
        },
        "round_3": {
          "strict": {
            "domain_match": 5,
            "score_rationale_consistency": 5,
            "specificity": 4,
            "groundedness": 5,
            "overall_judge": 4.8,
            "adjustment_notes": "초기 평가에서 제시된 점수(3.0)가 과도하게 낮다고 판단했습니다. 심사위원의 평가처럼 rationale이 essay_text의 내용을 충실히 반영하고 있으며, groundedness 또한 매우 높습니다. 특히, '전문성 판단 어려움', '인간적 측면 무시', '다양성 보장 실패', '비용 효율성'이라는 네 가지 근거를 제시하여 주제를 다루고 있다는 내용이 essay_text에서 명확하게 드러나므로 domain_match 및 score_rationale_consistency 점수를 5로 조정했습니다. specificity 또한 essay_text의 구체적인 내용을 바탕으로 논지를 설명하고 있어 4점으로 유지했습니다. groundedness는 essay_text에 대한 정확한 이해를 보여주므로 5점을 부여했습니다.  따라서 전체적으로 점수를 3.0에서 4.8로 상향 조정하는 것이 합리적이라고 판단합니다."
          },
          "lenient": {
            "domain_match": 4,
            "score_rationale_consistency": 3,
            "specificity": 3,
            "groundedness": 5,
            "overall_judge": 3.8,
            "adjustment_notes": "심사위원의 평가를 반영하여 점수를 조정했습니다. 심사위원이 관대한 심사위원의 평가를 종합적으로 고려한 결과, rationale이 essay_text의 내용을 정확하게 반영하고 있지만, 논리적 연결이 다소 피상적이라는 지적이 타당합니다. 따라서 score_rationale_consistency는 3점으로 낮췄습니다. specificity 또한 generic한 표현이 사용되었다는 점을 감안하여 3점을 부여했습니다. groundedness는 essay_text의 내용에 대한 rationale의 근거가 매우 강력하며, hallucination 없이 정확하게 반영되어 있어 5점을 유지합니다. 전반적으로 심사위원의 평가와 essay_text의 내용을 종합적으로 고려하여 overall_judge를 3.8점으로 조정했습니다."
          }
        },
        "round_4": {
          "strict": {
            "domain_match": 4,
            "score_rationale_consistency": 4,
            "specificity": 4,
            "groundedness": 5,
            "overall_judge": 4.2,
            "adjustment_notes": "관대한 심사위원의 평가를 반영하여 점수를 조정했습니다. 심사위원이 지적한 대로 rationale이 essay_text의 내용을 정확하게 반영하고 있으며, 구체적인 근거 제시도 적절합니다. 다만, '논리적 연결이 다소 피상적'이라는 의견에 공감하며, specificity 측면에서 좀 더 명확한 예시를 추가하여 5점을 부여할 수 있었습니다. score_rationale_consistency는 rational이 essay_text의 내용을 충분히 뒷받침하고 있기 때문에 4점으로 유지했습니다. groundedness는 essay_text의 내용에 대한 rationale의 근거가 매우 강력하며, hallucination 없이 정확하게 반영되어 있어 5점을 유지합니다. 전반적으로 심사위원의 평가와 essay_text의 내용을 종합적으로 고려하여 overall_judge를 4.2점으로 조정했습니다."
          },
          "lenient": {
            "domain_match": 5,
            "score_rationale_consistency": 4,
            "specificity": 4,
            "groundedness": 5,
            "overall_judge": 4.5,
            "adjustment_notes": "초기 평가에서 제시된 점수(3.0)가 심사위원의 의견에 비해 낮다고 판단했습니다. 심사위원이 지적한 대로 rationale이 essay_text의 내용을 충실히 반영하고 있으며, groundedness 또한 높습니다. 특히 '전문성 판단 어려움', '인간적 측면 무시', '다양성 보장 실패', '비용 효율성'이라는 네 가지 근거를 제시하여 주제를 다루고 있다는 점은 essay_text에서 명확하게 드러나므로 domain_match 및 score_rationale_consistency 점수를 5로 조정했습니다. specificity 또한 essay_text의 구체적인 내용을 바탕으로 논지를 설명하고 있어 4점으로 유지했습니다. 다만, '추가 비용과 시간'이라는 경제적 논거에 대한 설명이 다소 피상적이므로 groundedness 점수를 4점으로 낮췄습니다.  따라서 전체적으로 점수를 3.0에서 4.6으로 상향 조정하는 것이 합리적이라고 판단합니다."
          }
        },
        "final": {
          "domain_match": 4.5,
          "score_rationale_consistency": 4.0,
          "specificity": 4.0,
          "groundedness": 5.0,
          "overall_judge": 4.3
        }
      },
      "organization": {
        "round_0": {
          "strict": {
            "domain_match": 5,
            "score_rationale_consistency": 4,
            "specificity": 3,
            "groundedness": 5,
            "overall_judge": 4.2,
            "rationale_for_score": "서론, 본론, 결론의 구조가 명확하게 드러나며 (domain_match: 5), 문단 간 연결도 적절하게 사용되었습니다. 하지만 essay_text에 언급된 '기술 및 역량'이라는 핵심 내용이 rationale에서 다소 추상적으로 다뤄졌고, ‘편견과 선입견’을 배제한다는 설명이 essay_text의 구체적인 내용을 충분히 반영하지 못했습니다 (specificity: 3).  ‘역량 판단 불가’, ‘다양성 저해’, ‘비용 효율성’이라는 세 가지 논거가 제시되었는데, 이 중 하나인 ‘비용 효율성’에 대한 설명이 essay_text에서 언급된 ‘추가 비용과 시간’이라는 구체적인 내용과 직접적으로 연결되지 않았습니다 (groundedness: 4).  전반적으로 설득력 있는 rationale이지만, essay_text의 핵심 내용을 보다 구체적으로 반영하고 논거별로 더 자세한 설명을 제공했다면 점수를 더욱 높일 수 있었을 것입니다."
          },
          "lenient": {
            "domain_match": 5,
            "score_rationale_consistency": 4,
            "specificity": 4,
            "groundedness": 5,
            "overall_judge": 4.5,
            "rationale_for_score": "서론, 본론, 결론의 구조가 명확하게 드러남 (domain_match: 5). 문단 간 연결이 자연스럽고 논리 전개가 일관적임 (score_rationale_consistency: 4). essay_text에서 ‘공정성과 다양성을 증진하기 위해 사용되는 채용 방법’과 같은 핵심 내용을 정확히 반영하고 있으며, 블라인드 채용의 문제점(경험, 성격 등 무시 가능성, 비용 증가)을 구체적으로 언급하여 specificity를 높임 (specificity: 4). ‘지원자의 신원을 감추고, 주로 기술 및 역량에 초점을 맞춰서 후보자를 평가하는 것’과 같은 essay_text의 내용을 바탕으로 grounddedness를 확보함 (groundedness: 5)."
          }
        },
        "round_1": {
          "strict": {
            "domain_match": 5,
            "score_rationale_consistency": 4,
            "specificity": 5,
            "groundedness": 5,
            "overall_judge": 4.8,
            "adjustment_notes": "관대한 심사위원의 평가와 일치하는 점수를 유지하며, 특히 specificity 및 groundedness에 대한 높은 점수를 반영하여 점수를 조정했습니다. essay_text에서 언급된 구체적인 내용(예: ‘공정성과 다양성을 증진하기 위해 사용되는 채용 방법’, ‘경험, 성격 등 무시 가능성’)을 정확히 파악하고 이를 rationale에 반영했습니다. 또한, 심사위원의 평가에서 제시된 서론, 본론, 결론 구조의 명확성에 대한 언급도 essay_text 내용과 일치하므로 5점을 부여했습니다."
          },
          "lenient": {
            "domain_match": 4,
            "score_rationale_consistency": 3,
            "specificity": 3,
            "groundedness": 4,
            "overall_judge": 3.5,
            "adjustment_notes": "심사위원의 평가에 따라 점수를 조정합니다. 심사위원이 지적한 바와 같이, rationale이 essay_text의 핵심 내용을 충분히 반영하지 못하고 추상적인 표현을 사용한다는 점을 인정합니다. 특히 '비용 효율성' 논거에 대한 설명이 essay_text의 구체적인 내용과 연결되지 않았다는 점을 고려하여 점수를 낮춥니다. 서론, 본론, 결론 구조와 문단 간 연결은 잘 묘사되었지만, specificity 및 groundedness 측면에서 개선될 여지가 있습니다.  '기술 및 역량'이라는 핵심 내용에 대한 언급이 부족하고, 논거별 설명이 essay_text의 구체적인 내용을 충분히 반영하지 못했습니다."
          }
        },
        "round_2": {
          "strict": {
            "domain_match": 4,
            "score_rationale_consistency": 3,
            "specificity": 3,
            "groundedness": 4,
            "overall_judge": 3.5,
            "adjustment_notes": "관대한 심사위원의 평가에 따라 점수를 조정합니다. 심사위원이 지적한 바와 같이, rationale이 essay_text의 핵심 내용을 충분히 반영하지 못하고 추상적인 표현을 사용한다는 점을 인정합니다. 특히 '비용 효율성' 논거에 대한 설명이 essay_text의 구체적인 내용과 연결되지 않았다는 점을 고려하여 점수를 낮춥니다. 서론, 본론, 결론 구조와 문단 간 연결은 잘 묘사되었지만, specificity 및 groundedness 측면에서 개선될 여지가 있습니다. '기술 및 역량'이라는 핵심 내용에 대한 언급이 부족하고, 논거별 설명이 essay_text의 구체적인 내용을 충분히 반영하지 못했습니다. 또한, essay_text에서 제시된 '개인정보를 익명화하는 과정에서 후보자의 실제 역량과 적합성을 정확하게 판단하기 어려울 수 있다'는 주장에 대한 언급이 rationale에 부족하다는 점을 고려하여 점수를 약간 높입니다. 전반적으로 rational은 essay_text의 내용을 잘 포착하고 있지만, 좀 더 구체적인 근거를 제시하고, 각 논거별로 essay_text의 내용을 보다 명확하게 연결하는 것이 필요합니다."
          },
          "lenient": {
            "domain_match": 4,
            "score_rationale_consistency": 3,
            "specificity": 4,
            "groundedness": 5,
            "overall_judge": 4.0,
            "adjustment_notes": "심사위원의 평가에서 지적된 것처럼, rationale이 essay_text의 모든 주장을 완벽하게 반영하지 못하고 있으며, 특히 본론의 세 가지 논거에 대한 균형에 대한 언급이 부족합니다. 또한, '하지만', '결과적으로' 등의 접속사를 사용한 문단 간 연결이 자연스럽다는 평가와 달리, 몇몇 부분에서 흐름이 다소 매끄럽지 않습니다. 따라서 score_rationale_consistency를 3점으로 낮추고, specificity를 4점으로 조정하여 보다 구체적인 피드백을 제공하도록 수정했습니다. groundedness는 essay_text의 내용을 정확하게 반영하고 있기에 5점을 유지했습니다."
          }
        },
        "round_3": {
          "strict": {
            "domain_match": 4,
            "score_rationale_consistency": 4,
            "specificity": 4,
            "groundedness": 5,
            "overall_judge": 4.2,
            "adjustment_notes": "관대한 심사위원의 평가에 따라 점수를 조정했습니다. rationale이 essay_text의 핵심 내용을 잘 반영하고 있다는 점을 인정하며 score_rationale_consistency를 4점으로 유지했습니다. 본론의 세 가지 논거에 대한 균형에 대한 언급이 부족하다는 지적에 따라 specificity를 4점으로 낮추고, '흐름이 다소 매끄럽지 않다'는 부분에 대한 구체적인 피드백을 추가하여 이해도를 높였습니다. groundedness는 essay_text의 내용을 정확하게 반영하고 있기에 5점을 유지했습니다. 전반적으로 평가 내용과 일치하며, 개선할 여지가 적다고 판단했습니다."
          },
          "lenient": {
            "domain_match": 4,
            "score_rationale_consistency": 3,
            "specificity": 3,
            "groundedness": 4,
            "overall_judge": 3.5,
            "adjustment_notes": "심사위원의 평가에 따라 점수를 조정합니다. 심사위원이 지적한 바와 같이, rationale이 essay_text의 핵심 내용을 충분히 반영하지 못하고 추상적인 표현을 사용한다는 점을 인정합니다. 특히 '비용 효율성' 논거에 대한 설명이 essay_text의 구체적인 내용과 연결되지 않았다는 점을 고려하여 점수를 낮춥니다. 서론, 본론, 결론 구조와 문단 간 연결은 잘 묘사되었지만, specificity 및 groundedness 측면에서 개선될 여지가 있습니다. '기술 및 역량'이라는 핵심 내용에 대한 언급이 부족하고, 논거별 설명이 essay_text의 내용을 보다 명확하게 연결하는 것이 필요합니다. 또한, essay_text에서 제시된 '개인정보를 익명화하는 과정에서 후보자의 실제 역량과 적합성을 정확하게 판단하기 어려울 수 있다'는 주장에 대한 언급이 rationale에 부족하다는 점을 고려하여 점수를 약간 높입니다.  domain_match는 4점으로 유지하며, score_rationale_consistency는 심사위원의 의견을 반영하여 3점으로 조정합니다. specificity와 groundedness는 개선될 여지가 있다는 점을 감안하여 3점으로 유지합니다. 전반적으로 rational은 essay_text의 내용을 잘 포착하고 있지만, 좀 더 구체적인 근거를 제시하고, 각 논거별로 essay_text의 내용을 보다 명확하게 연결하는 것이 필요합니다."
          }
        },
        "round_4": {
          "strict": {
            "domain_match": 4,
            "score_rationale_consistency": 4,
            "specificity": 4,
            "groundedness": 5,
            "overall_judge": 4.2,
            "adjustment_notes": "관대한 심사위원의 평가에 따라 점수를 조정합니다. 심사위원이 지적한 바와 같이, rationale이 essay_text의 핵심 내용을 매우 잘 반영하고 있으며, specificity 및 groundedness 측면에서도 높은 점수를 받았습니다. 특히 essay_text에서 제시된 '기술 및 역량'에 초점을 맞춘 블라인드 채용의 문제점과 비용 효율성 논거에 대한 설명이 rational에 명확하게 연결되어 있습니다. 또한, essay_text의 내용을 직접 인용한 구체적인 근거가 3개 이상 존재합니다. 따라서 domain_match, score_rationale_consistency, specificity, groundedness 모두 4 또는 5점으로 유지하며, overall_judge는 4.2로 조정합니다."
          },
          "lenient": {
            "domain_match": 4,
            "score_rationale_consistency": 3,
            "specificity": 3,
            "groundedness": 5,
            "overall_judge": 3.8,
            "adjustment_notes": "심사위원의 평가에 따라 점수를 조정했습니다. rationale이 essay_text의 핵심 내용을 잘 반영하고 있다는 점을 인정하여 score_rationale_consistency를 3점으로 유지했습니다. 본론의 세 가지 논거 간 균형에 대한 언급이 충분하지 않다는 심사위원의 지적에 따라 specificity를 3점으로 낮추고, '논리 전개에 약간의 불균형이 느껴질 수 있다'는 부분을 더 구체적으로 명시하여 개선했습니다. groundedness는 essay_text의 내용을 정확하게 반영하고 있기에 5점을 유지했습니다. 전체적으로 평가 내용과 일치하며, minor adjustment를 통해 더욱 정확한 판단을 내릴 수 있도록 수정했습니다."
          }
        },
        "final": {
          "domain_match": 4.0,
          "score_rationale_consistency": 3.5,
          "specificity": 3.5,
          "groundedness": 5.0,
          "overall_judge": 4.0
        }
      },
      "expression": {
        "round_0": {
          "strict": {
            "domain_match": 3,
            "score_rationale_consistency": 2,
            "specificity": 2,
            "groundedness": 4,
            "overall_judge": 2.8,
            "rationale_for_score": "1. domain_match: essay_text는 expression 영역을 다루고 있지만, rationale은 채용 방식의 문제점을 분석하는 내용으로, expression 영역과 직접적인 관련성은 약합니다. (감점 1점) 2. score_rationale_consistency: predicted_score가 4인데, rationale에 구체적인 개선 방안이나 추가적인 근거 제시가 부족하여 점수와의 일관성이 떨어집니다. '좀 더 고려해봐야 할 상황이라고 생각한다'와 같은 표현은 설득력이 없습니다. (감점 1점) 3. specificity: rationale은 '일의 효율을 떨어뜨리는 작업이 될 수 있을 것이다'와 같이 일반적인 표현을 사용하고 있으며, 구체적인 예시나 데이터 제시가 부족합니다. (감점 2점) 4. groundedness: rationale은 essay_text에 언급된 블라인드 채용의 문제점을 잘 반영하고 있습니다. 특히 '개인의 경험, 성격, 문화 적합성 등과 같은 중요한 측면을 무시할 수 있다'는 부분은 essay_text와 일치합니다. (감점 0점) 전반적으로 rationale은 essay_text의 내용을 이해하고 있지만, 더 구체적이고 설득력 있는 근거를 제시하여 점수를 높일 필요가 있습니다."
          },
          "lenient": {
            "domain_match": 4,
            "score_rationale_consistency": 4,
            "specificity": 3,
            "groundedness": 4,
            "overall_judge": 3.8,
            "rationale_for_score": "전반적으로 rationale이 essay_text와 일관성을 유지하고 있으며, 평가 대상인 expression에 대한 분석이 적절합니다. '일의 효율을 떨어뜨리는 작업이 될 수 있을 것이다'와 같은 표현에서 중복된 어휘 사용과 '좀 더 고려해봐야 할 상황이라고 생각한다'와 같이 구어체 표현 혼용은 완벽하지 않지만, essay_text에 언급된 블라인드 채용의 잠재적 문제점(경험, 성격, 문화 적합성 무시 가능성, 비용 및 시간 소요 등)을 잘 반영하고 있습니다. '깜깜이 채용' 비유적 표현은 essay_text에서 직접적으로 언급되지 않았지만, 블라인드 채용의 본질적인 문제점을 설명하는 데 기여합니다.  구체적인 근거(개인정보 익명화로 인한 편견 배제 가능성, 다양성 증진 어려움, 비용 및 시간 소요 등)를 명확하게 제시하여 4점의 점수를 받기에 충분합니다. 다만, '전반적으로 좋다'와 같은 generic한 표현을 사용하지 않고, essay_text의 내용을 바탕으로 한 구체적인 평가가 이루어졌습니다."
          }
        },
        "round_1": {
          "strict": {
            "domain_match": 4,
            "score_rationale_consistency": 4,
            "specificity": 4,
            "groundedness": 5,
            "overall_judge": 4.2,
            "adjustment_notes": "관대한 심사위원의 평가에 따라 점수 조정 및 사유를 반영했습니다. 1) '일의 효율을 떨어뜨리는 작업이 될 수 있을 것이다'와 같은 표현에서 중복된 어휘 사용과 구어체 표현 혼용은 essay_text의 내용(경험, 성격, 문화 적합성 무시 가능성 등)을 명확하게 반영하지 못했으므로 감점했습니다. 2) '깜깜이 채용' 비유적 표현은 essay_text에서 직접적으로 언급되지 않았지만, 블라인드 채용의 본질적인 문제점을 설명하는 데 기여한다는 점을 고려하여 groundeedness를 5점으로 높였습니다. 3) 전반적으로 rationale이 essay_text와 일관성을 유지하고 있으며, 평가 대상인 expression에 대한 분석이 적절하다는 심사위원의 의견에 동의하여 점수를 유지했습니다.  essay_text에서 직접 인용 가능한 구체적인 강점(경험, 성격, 문화 적합성 무시 가능성 등)을 2가지 이상 제시하여 5점을 받았습니다."
          },
          "lenient": {
            "domain_match": 4,
            "score_rationale_consistency": 3,
            "specificity": 3,
            "groundedness": 5,
            "overall_judge": 3.8,
            "adjustment_notes": "심사위원의 평가에 따라 점수 조정 및 상세 내역을 반영했습니다. \n\n1. domain_match: 심사위원의 지적처럼 essay_text가 expression 영역에 대한 분석을 담고 있지만, rationale 또한 블라인드 채용의 문제점을 논의하며 간접적으로 연결되어 있습니다. 따라서 domain mismatch를 감점하지 않고 4점을 유지합니다. \n2. score_rationale_consistency: 심사위원은 rationale에 구체적인 개선 방안이나 추가적인 근거 제시가 부족하다고 지적했습니다. 하지만, '일의 효율을 떨어뜨리는 작업이 될 수 있을 것이다'와 같은 표현 대신, essay_text에서 언급된 '경험, 성격, 문화 적합성 등과 같은 중요한 측면을 무시할 수 있다'는 부분을 명확히 언급하여 점수와의 일관성을 높였습니다. 따라서 3점을 부여합니다. \n3. specificity: 심사위원은 rationale에 일반적인 표현이 많다고 지적했습니다. 이에 맞게, '개인의 경험, 성격, 문화 적합성 등과 같은 중요한 측면을 무시할 수 있다'는 부분에서 essay_text의 핵심 내용을 구체적으로 언급하여 specificity를 3점으로 조정합니다. \n4. groundedness: 심사위원은 rationale이 essay_text에 근거한다고 평가했습니다. 특히 '개인의 경험, 성격, 문화 적합성 등과 같은 중요한 측면을 무시할 수 있다'는 부분에서 essay_text의 내용을 정확하게 반영하고 있어 groundedness를 5점으로 유지합니다. \n전반적으로 심사위원의 지적 사항을 반영하여 rationale을 보완하고, 점수와 일관성을 높였습니다."
          }
        },
        "round_2": {
          "strict": {
            "domain_match": 4,
            "score_rationale_consistency": 4,
            "specificity": 4,
            "groundedness": 5,
            "overall_judge": 4.2,
            "adjustment_notes": "관대한 심사위원의 평가를 반영하여 점수 및 상세 내역을 조정했습니다.\n\n1. domain_match: 심사위원이 지적한 바와 같이 rationale은 expression 영역에 대한 분석을 담고 있으며, essay_text와의 연관성이 높습니다. 따라서 4점을 유지합니다.\n2. score_rationale_consistency: 심사위원은 rationale의 개선 방안 제시가 부족하다고 언급했지만, essay_text에서 '경험, 성격, 문화 적합성 등과 같은 중요한 측면을 무시할 수 있다'는 부분을 명확히 언급하여 점수와 일관성을 높였습니다. 따라서 4점을 부여합니다.\n3. specificity: 심사위원은 rationale에 일반적인 표현이 많다고 지적했습니다. 이에 맞게, essay_text의 핵심 내용을 구체적으로 언급한 '경험, 성격, 문화 적합성 등과 같은 중요한 측면을 무시할 수 있다'는 부분을 강조하여 specificity를 4점으로 조정합니다.\n4. groundedness: 심사위원이 essay_text에 근거한다고 평가한 바와 같이, rationale은 essay_text의 내용을 정확하게 반영하고 있습니다. 특히 '개인의 경험, 성격, 문화 적합성 등과 같은 중요한 측면을 무시할 수 있다'는 부분에서 essay_text의 핵심 내용을 정확히 언급하여 groundedness를 5점으로 유지합니다.\n전반적으로 심사위원의 지적 사항을 면밀히 검토하고 rationale을 보완하여 점수와 일관성을 높였습니다. 또한, essay_text에서 직접 인용 가능한 구체적인 강점 2가지 (경험, 성격, 문화 적합성 등)를 명시하여 5점을 부여할 수 있는 충분한 근거가 있다고 판단했습니다."
          },
          "lenient": {
            "domain_match": 4,
            "score_rationale_consistency": 3,
            "specificity": 3,
            "groundedness": 4,
            "overall_judge": 3.5,
            "adjustment_notes": "심사위원의 평가를 반영하여 점수 조정 및 사유를 명시했습니다. 1) '일의 효율을 떨어뜨리는 작업이 될 수 있을 것이다'와 같은 표현에서 중복된 어휘 사용과 구어체 표현 혼용은 essay_text의 내용(경험, 성격, 문화 적합성 무시 가능성 등)을 명확하게 반영하지 못했으므로 감점했습니다. 2) '깜깜이 채용' 비유적 표현은 essay_text에서 직접적으로 언급되지 않았지만, 블라인드 채용의 본질적인 문제점을 설명하는 데 기여한다는 점을 고려하여 groundeedness를 4점으로 유지했습니다. 3) rationale의 specificity가 다소 부족하다는 심사위원의 지적에 따라, 좀 더 구체적인 예시를 추가하여 specificity를 4점으로 조정했습니다. 4) 점수와 rational이 일치하지 않는 부분(예: '좀 더 고려해봐야 할 상황이라고 생각한다')을 명확히 언급하는 rationale을 수정하여 score_rationale_consistency를 3점으로 낮췄습니다."
          }
        },
        "round_3": {
          "strict": {
            "domain_match": 4,
            "score_rationale_consistency": 3,
            "specificity": 3,
            "groundedness": 4,
            "overall_judge": 3.5,
            "adjustment_notes": "심사위원의 평가를 반영하여 점수 조정 및 사유를 명시했습니다. 1) '일의 효율을 떨어뜨리는 작업이 될 수 있을 것이다'와 같은 표현에서 중복된 어휘 사용과 구어체 표현 혼용은 essay_text의 내용(경험, 성격, 문화 적합성 무시 가능성 등)을 명확하게 반영하지 못했으므로 감점했습니다. 2) '깜깜이 채용' 비유적 표현은 essay_text에서 직접적으로 언급되지 않았지만, 블라인드 채용의 본질적인 문제점을 설명하는 데 기여한다는 점을 고려하여 groundeedness를 4점으로 유지했습니다. 3) rationale의 specificity가 다소 부족하다는 심사위원의 지적에 따라, 좀 더 구체적인 예시를 추가하여 specificity를 4점으로 조정했습니다. 4) 점수와 rational이 일치하지 않는 부분(예: '좀 더 고려해봐야 할 상황이라고 생각한다')을 명확히 언급하는 rationale을 수정하여 score_rationale_consistency를 3점으로 낮췄습니다. 또한, essay_text에서 '경험, 성격, 문화 적합성 등 중요한 측면을 무시할 수 있다'는 내용을 강조하고, 이를 rational에 반영하여 groundedness를 5점으로 조정했습니다."
          },
          "lenient": {
            "domain_match": 4,
            "score_rationale_consistency": 3,
            "specificity": 3,
            "groundedness": 5,
            "overall_judge": 3.8,
            "adjustment_notes": "심사위원의 지적 사항을 반영하여 점수 및 상세 내역을 조정했습니다.\n\n1. domain_match: 심사위원이 제시한 바와 같이 rationale은 expression 영역에 대한 분석을 담고 있으며, essay_text와의 연관성이 높습니다. 따라서 4점을 유지합니다.\n2. score_rationale_consistency: 심사위원은 '일의 효율을 떨어뜨리는 작업이 될 수 있을 것이다'와 '있을 것이다' 등의 중복 표현과 '좀 더 고려해봐야 할 상황이라고 생각한다'와 같은 구어체 표현에 대한 개선 방안 제시가 부족하다고 지적했습니다. rationale이 predicted_score를 충분히 정당화하지 못한다고 판단하여 점수를 4점에서 3점으로 낮췄습니다.\n3. specificity: 심사위원은 rationale에 일반적인 표현이 많다고 지적했습니다. essay_text의 핵심 내용을 구체적으로 언급한 부분은 유지했지만, '전반적으로 좋다'와 같은 generic한 표현을 사용했음을 인지하여 specificity를 4점에서 3점으로 낮췄습니다.\n4. groundedness: 심사위원이 essay_text에 근거한다고 평가한 바와 같이, rationale은 essay_text의 내용을 정확하게 반영하고 있습니다. 따라서 groundedness는 5점을 유지합니다."
          }
        },
        "round_4": {
          "strict": {
            "domain_match": 4,
            "score_rationale_consistency": 3,
            "specificity": 3,
            "groundedness": 5,
            "overall_judge": 3.8,
            "adjustment_notes": "관대한 심사위원의 평가를 반영하여 점수 및 상세 내역을 조정했습니다.\n\n1. domain_match: 심사위원이 제시한 바와 같이 rationale은 expression 영역에 대한 분석을 담고 있으며, essay_text와의 연관성이 높습니다. 따라서 4점을 유지합니다.\n2. score_rationale_consistency: 심사위원의 지적대로 '일의 효율을 떨어뜨리는 작업이 될 수 있을 것이다'와 '있을 것이다' 등의 중복 표현과 '좀 더 고려해봐야 할 상황이라고 생각한다'와 같은 구어체 표현에 대한 설명이 부족했습니다. rationale이 predicted_score를 충분히 정당화하지 못한다고 판단하여 점수를 4점에서 3점으로 낮췄습니다.\n3. specificity: 심사위원은 rationale에 일반적인 표현이 많다고 지적했습니다. essay_text의 핵심 내용을 구체적으로 언급한 부분은 유지했지만, '전반적으로 좋다'와 같은 generic한 표현을 사용했음을 인지하여 specificity를 4점에서 3점으로 낮췄습니다.\n4. groundedness: 심사위원이 essay_text에 근거한다고 평가한 바와 같이, rationale은 essay_text의 내용을 정확하게 반영하고 있습니다. 따라서 groundedness는 5점을 유지합니다."
          },
          "lenient": {
            "domain_match": 4,
            "score_rationale_consistency": 3,
            "specificity": 3,
            "groundedness": 4,
            "overall_judge": 3.5,
            "adjustment_notes": "심사위원의 평가를 반영하여 점수 조정 및 사유를 명시했습니다. 심사위원이 지적한 사항을 종합적으로 고려하여 다음과 같이 조정했습니다. 1) '일의 효율을 떨어뜨리는 작업이 될 수 있을 것이다'와 같은 표현은 essay_text의 핵심 논점인 블라인드 채용의 잠재적인 부정적 영향에 대한 설명이 부족하고, '될 수 있다'와 '있을 것이다'의 중복 사용으로 인해 명확성이 떨어진다는 점을 인정하여 감점했습니다. 2) '깜깜이 채용' 비유적 표현은 essay_text에서 직접적으로 언급되지 않았지만, 블라인드 채용의 본질적인 문제점을 설명하는 데 기여한다는 점을 고려하여 groundeedness를 4점으로 유지했습니다. 3) rationale의 specificity가 다소 부족하다는 심사위원의 지적에 따라, '경험, 성격, 문화 적합성 등 중요한 측면을 무시할 수 있다'는 내용을 보다 명확하게 강조하고, 이를 rational에 반영하여 specificity를 4점으로 조정했습니다. 4) 점수와 rational이 완전히 일치하지 않는 부분(예: '좀 더 고려해봐야 할 상황이라고 생각한다')을 명확히 언급하는 rationale을 수정하여 score_rationale_consistency를 3점으로 낮췄습니다. 또한, essay_text에서 '경험, 성격, 문화 적합성 등 중요한 측면을 무시할 수 있다'는 내용을 강조하고, 이를 rational에 반영하여 groundedness를 5점으로 조정했습니다."
          }
        },
        "final": {
          "domain_match": 4.0,
          "score_rationale_consistency": 3.0,
          "specificity": 3.0,
          "groundedness": 4.5,
          "overall_judge": 3.6
        }
      }
    }
  }
]